<item>
<title>[B][COLOR gold]l[/COLOR] [COLOR white]PRÓXIMA PÁGINA: [COLOR gold]3[/COLOR][/COLOR][/B]</title>
<link>here</link>
<thumbnail>https://i.imgur.com/osBDac3.jpg</thumbnail>
<externallink>https://raw.github.com/skyrisk/brazucaplay/master/outros/filmes/letra/Letra-B3.xml</externallink>
<info>[B][COLOR white]TODOS OS MELHORES FILMES EM [COLOR gold]ORDEM ALFABÉTICA[/COLOR][/COLOR][/B]</info>
<fanart>https://i.imgur.com/225XKdt.jpg</fanart>
</item>
<item>
<title>[B][COLOR white]BENZINHO[/COLOR] - [COLOR gold]7.2[/COLOR][/B]</title>
<link>movie=29180.mp4</link>
<info>Duração do filme: 1h, 38min</info>
<genre>Drama</genre>
<date>2018</date>
</item>
<item>
<title>[B][COLOR white]BEOWULF, O GUERREIRO DAS SOMBRAS[/COLOR] - [COLOR gold]4.1[/COLOR][/B]</title>
<link>movie=28442.mp4</link>
<info>Duração do filme: 1h, 35min</info>
<genre>Ação, Sci-Fi, Suspense, Aventura, Terror, Fantasia</genre>
<date>1999</date>
</item>
<item>
<title>[B][COLOR white]BERENICE PROCURA[/COLOR] - [COLOR gold]6.2[/COLOR][/B]</title>
<link>movie=15020.mp4</link>
<info>Duração do filme: 1h, 30min</info>
<genre></genre>
<date>2017</date>
</item>
<item>
<title>[B][COLOR white]BERKSHIRE COUNTY[/COLOR] - [COLOR gold]4.8[/COLOR][/B]</title>
<link>movie=13659.mp4</link>
<info>Duração do filme: 1h, 23min</info>
<genre>Terror, Suspense</genre>
<date>2014</date>
</item>
<item>
<title>[B][COLOR white]BERLIM, BERLIM – LOLLE E SUAS OPÇÕES[/COLOR] - [COLOR gold]3.4[/COLOR][/B]</title>
<link>movie=27260.mp4</link>
<info>Duração do filme: 1h, 20min</info>
<genre>Comédia, Drama, Romance</genre>
<date>2020</date>
</item>
<item>
<title>[B][COLOR white]BERLIN CALLING[/COLOR] - [COLOR gold]7.3[/COLOR][/B]</title>
<link>movie=23576.mp4</link>
<info>Duração do filme: 1h, 45min</info>
<genre>Comédia, Drama, Músical</genre>
<date>2008</date>
</item>
<item>
<title>[B][COLOR white]BERLIN, I LOVE YOU[/COLOR] - [COLOR gold]4.6[/COLOR][/B]</title>
<link>movie=13873.mp4</link>
<info>Duração do filme: 2h, 0min</info>
<genre>Drama</genre>
<date>2019</date>
</item>
<item>
<title>[B][COLOR white]BERMUDA TENTACLES[/COLOR] - [COLOR gold]3.5[/COLOR][/B]</title>
<link>movie=14214.mp4</link>
<info>Duração do filme: 2h, 6min</info>
<genre>Sci-Fi</genre>
<date>2014</date>
</item>
<item>
<title>[B][COLOR white]BERNARDO E BIANCA NA TERRA DOS CANGURUS[/COLOR][/B]</title>
<link>movie=29195.mp4</link>
<info>Duração do filme: 1h, 17min</info>
<genre>Aventura, Animação, Família, Fantasia</genre>
<date>1990</date>
</item>
<item>
<title>[B][COLOR white]BERNARDO E BIANCA[/COLOR] - [COLOR gold]6.9[/COLOR][/B]</title>
<link>movie=15974.mp4</link>
<info>Duração do filme: 1h, 18min</info>
<genre>Fantasia, Família, Animação, Aventura</genre>
<date>1977</date>
</item>
<item>
<title>[B][COLOR white]BERNIE, O GOLFINHO[/COLOR][/B]</title>
<link>movie=29484.mp4</link>
<info>Duração do filme: 1h, 28min</info>
<genre>Ação, Comédia, Família, Aventura</genre>
<date>2018</date>
</item>
<item>
<title>[B][COLOR white]BERNIE: QUASE UM ANJO[/COLOR] - [COLOR gold]6.8[/COLOR][/B]</title>
<link>movie=23778.mp4</link>
<info>Duração do filme: 1h, 39min</info>
<genre>Comédia, Crime, Drama</genre>
<date>2012</date>
</item>
<item>
<title>[B][COLOR white]BERSERK - A ERA DE OURO, ATO 1: OVO DO REI SUPREMO[/COLOR] - [COLOR gold]7.6[/COLOR][/B]</title>
<link>movie=18238.mp4</link>
<info>Duração do filme: 1h, 20min</info>
<genre>Ação, Aventura, Fantasia, Animação</genre>
<date>2012</date>
</item>
<item>
<title>[B][COLOR white]BERSERK - A ERA DE OURO, ATO 2: A BATALHA DE DOLDREY[/COLOR] - [COLOR gold]7.8[/COLOR][/B]</title>
<link>movie=17480.mp4</link>
<info>Duração do filme: 1h, 50min</info>
<genre>Ação, Aventura, Drama, Fantasia, Animação</genre>
<date>2012</date>
</item>
<item>
<title>[B][COLOR white]BERSERK - A ERA DE OURO, ATO 3: A QUEDA[/COLOR] - [COLOR gold]7.9[/COLOR][/B]</title>
<link>movie=16682.mp4</link>
<info>Duração do filme: 1h, 20min</info>
<genre>Ação, Aventura, Drama, Fantasia, Animação</genre>
<date>2013</date>
</item>
<item>
<title>[B][COLOR white]BERT KREISCHER: HEY BIG BOY[/COLOR] - [COLOR gold]7.1[/COLOR][/B]</title>
<link>movie=26785.mp4</link>
<info>Duração do filme: 1h, 2min</info>
<genre>Comédia</genre>
<date>2020</date>
</item>
<item>
<title>[B][COLOR white]BESETMENT[/COLOR] - [COLOR gold]3.6[/COLOR][/B]</title>
<link>movie=15261.mp4</link>
<info>Duração do filme: 1h, 16min</info>
<genre>Suspense, Terror</genre>
<date>2016</date>
</item>
<item>
<title>[B][COLOR white]BESOURO[/COLOR] - [COLOR gold]5.8[/COLOR][/B]</title>
<link>movie=18501.mp4</link>
<info>Duração do filme: 1h, 30min</info>
<genre>Drama, Ação, Aventura</genre>
<date>2009</date>
</item>
<item>
<title>[B][COLOR white]BESSIE[/COLOR] - [COLOR gold]6.6[/COLOR][/B]</title>
<link>movie=24104.mp4</link>
<info>Duração do filme: 2h, 12min</info>
<genre>Drama, Músical, tv movie</genre>
<date>2015</date>
</item>
<item>
<title>[B][COLOR white]BEST DAY EVER[/COLOR] - [COLOR gold]3.8[/COLOR][/B]</title>
<link>movie=21675.mp4</link>
<info>Duração do filme: 1h, 22min</info>
<genre>Romance, Drama</genre>
<date>2014</date>
</item>
<item>
<title>[B][COLOR white]BEST NIGHT EVER[/COLOR] - [COLOR gold]4.0[/COLOR][/B]</title>
<link>movie=17291.mp4</link>
<info>Duração do filme: 1h, 30min</info>
<genre>Comédia</genre>
<date>2014</date>
</item>
<item>
<title>[B][COLOR white]BETA TEST[/COLOR] - [COLOR gold]5.9[/COLOR][/B]</title>
<link>movie=18814.mp4</link>
<info>Duração do filme: 1h, 28min</info>
<genre>Suspense, Ação, Sci-Fi</genre>
<date>2016</date>
</item>
<item>
<title>[B][COLOR white]BETÃO RONCA FERRO[/COLOR] - [COLOR gold]7.0[/COLOR][/B]</title>
<link>movie=29719.mp4</link>
<info>Duração do filme: 1h, 40min</info>
<genre>Comédia</genre>
<date>1970</date>
</item>
<item>
<title>[B][COLOR white]BETHÂNIA BEM DE PERTO: A PROPÓSITO DE UM SHOW[/COLOR][/B]</title>
<link>movie=28022.mp4</link>
<info>Duração do filme: h, 33min</info>
<genre>Documentário, Músical</genre>
<date>1966</date>
</item>
<item>
<title>[B][COLOR white]BETHANY[/COLOR] - [COLOR gold]5.0[/COLOR][/B]</title>
<link>movie=24322.mp4</link>
<info>Duração do filme: 1h, 20min</info>
<genre>Terror</genre>
<date>2017</date>
</item>
<item>
<title>[B][COLOR white]BETRAYED[/COLOR] - [COLOR gold]5.5[/COLOR][/B]</title>
<link>movie=23907.mp4</link>
<info>Duração do filme: 1h, 37min</info>
<genre>Crime, Ação, Suspense</genre>
<date>2018</date>
</item>
<item>
<title>[B][COLOR white]BETTER THAN CHOCOLATE[/COLOR] - [COLOR gold]6.1[/COLOR][/B]</title>
<link>movie=14957.mp4</link>
<info>Duração do filme: 1h, 41min</info>
<genre>Drama, Romance, Lgbt</genre>
<date>1999</date>
</item>
<item>
<title>[B][COLOR white]BETTIE PAGE REVEALS ALL[/COLOR] - [COLOR gold]7.1[/COLOR][/B]</title>
<link>movie=17565.mp4</link>
<info>Duração do filme: 1h, 41min</info>
<genre>Documentário</genre>
<date>2013</date>
</item>
<item>
<title>[B][COLOR white]BETTING ON ZERO[/COLOR] - [COLOR gold]7.2[/COLOR][/B]</title>
<link>movie=19475.mp4</link>
<info>Duração do filme: 1h, 39min</info>
<genre>Documentário</genre>
<date>2017</date>
</item>
<item>
<title>[B][COLOR white]BETWEEN TWO FERNS - O FILME[/COLOR] - [COLOR gold]6.1[/COLOR][/B]</title>
<link>movie=17356.mp4</link>
<info>Duração do filme: 1h, 22min</info>
<genre>Comédia</genre>
<date>2019</date>
</item>
<item>
<title>[B][COLOR white]BETWEEN[/COLOR] - [COLOR gold]4.2[/COLOR][/B]</title>
<link>movie=21034.mp4</link>
<info>Duração do filme: 1h, 20min</info>
<genre>Suspense</genre>
<date>2005</date>
</item>
<item>
<title>[B][COLOR white]BEWARE, MY LOVELY[/COLOR] - [COLOR gold]6.7[/COLOR][/B]</title>
<link>movie=17103.mp4</link>
<info>Duração do filme: 1h, 17min</info>
<genre>Drama, Crime</genre>
<date>1952</date>
</item>
<item>
<title>[B][COLOR white]BEYOND LOCH NESS[/COLOR] - [COLOR gold]4.0[/COLOR][/B]</title>
<link>movie=26666.mp4</link>
<info>Duração do filme: 1h, 31min</info>
<genre>Sci-Fi, Terror, Suspense, Mistério</genre>
<date>2008</date>
</item>
<item>
<title>[B][COLOR white]BEYOND THE CLOUDS[/COLOR] - [COLOR gold]6.9[/COLOR][/B]</title>
<link>movie=15817.mp4</link>
<info>Duração do filme: 2h, 0min</info>
<genre>Família, Drama</genre>
<date>2018</date>
</item>
<item>
<title>[B][COLOR white]BEYOND THE EDGE[/COLOR] - [COLOR gold]6.8[/COLOR][/B]</title>
<link>movie=19267.mp4</link>
<info>Duração do filme: 1h, 33min</info>
<genre>Documentário, Drama</genre>
<date>2013</date>
</item>
<item>
<title>[B][COLOR white]BEYOND THE GATES[/COLOR] - [COLOR gold]5.2[/COLOR][/B]</title>
<link>movie=17057.mp4</link>
<info>Duração do filme: 1h, 24min</info>
<genre>Aventura, Terror</genre>
<date>2016</date>
</item>
<item>
<title>[B][COLOR white]BEYOND THE LAW[/COLOR] - [COLOR gold]4.4[/COLOR][/B]</title>
<link>movie=25757.mp4</link>
<info>Duração do filme: 1h, 30min</info>
<genre>Ação, Aventura, Mistério</genre>
<date>2019</date>
</item>
<item>
<title>[B][COLOR white]BEYOND THE LAW[/COLOR] - [COLOR gold]6.6[/COLOR][/B]</title>
<link>movie=25409.mp4</link>
<info>Duração do filme: 1h, 48min</info>
<genre>Ação</genre>
<date>1993</date>
</item>
<item>
<title>[B][COLOR white]BEYOND THE SEA[/COLOR] - [COLOR gold]6.7[/COLOR][/B]</title>
<link>movie=21126.mp4</link>
<info>Duração do filme: 1h, 58min</info>
<genre>Drama, Músical</genre>
<date>2004</date>
</item>
<item>
<title>[B][COLOR white]BEYOND THE SKY[/COLOR] - [COLOR gold]5.8[/COLOR][/B]</title>
<link>movie=21795.mp4</link>
<info>Duração do filme: 1h, 25min</info>
<genre>Sci-Fi, Terror, Mistério, Suspense</genre>
<date>2018</date>
</item>
<item>
<title>[B][COLOR white]BEYOND THE TROPHY[/COLOR] - [COLOR gold]4.9[/COLOR][/B]</title>
<link>movie=26665.mp4</link>
<info>Duração do filme: 1h, 20min</info>
<genre>Ação, Crime</genre>
<date>2012</date>
</item>
<item>
<title>[B][COLOR white]BEYOND THE WOODS[/COLOR] - [COLOR gold]5.6[/COLOR][/B]</title>
<link>movie=14759.mp4</link>
<info>Duração do filme: 1h, 24min</info>
<genre>Terror</genre>
<date>2018</date>
</item>
<item>
<title>[B][COLOR white]BEYOND WHITE SPACE[/COLOR] - [COLOR gold]4.5[/COLOR][/B]</title>
<link>movie=19166.mp4</link>
<info>Duração do filme: 1h, 33min</info>
<genre>Sci-Fi, Suspense</genre>
<date>2018</date>
</item>
<item>
<title>[B][COLOR white]BEYOND[/COLOR] - [COLOR gold]3.9[/COLOR][/B]</title>
<link>movie=18342.mp4</link>
<info>Duração do filme: 1h, 29min</info>
<genre>Romance, Sci-Fi, Drama</genre>
<date>2014</date>
</item>
<item>
<title>[B][COLOR white]BIA (2.0)[/COLOR] - [COLOR gold]5.1[/COLOR][/B]</title>
<link>movie=22111.mp4</link>
<info>Duração do filme: 1h, 30min</info>
<genre>Romance</genre>
<date>2018</date>
</item>
<item>
<title>[B][COLOR white]BIA: UM MUNDO DO AVESSO[/COLOR] - [COLOR gold]6.9[/COLOR][/B]</title>
<link>movie=28145.mp4</link>
<info>Duração do filme: 1h, 31min</info>
<genre>Comédia, Drama, Família</genre>
<date>2021</date>
</item>
<item>
<title>[B][COLOR white]BIBI & TINA: GIRLS VS. BOYS[/COLOR] - [COLOR gold]5.4[/COLOR][/B]</title>
<link>movie=25955.mp4</link>
<info>Duração do filme: 1h, 51min</info>
<genre>Família, Fantasia, Comédia</genre>
<date>2016</date>
</item>
<item>
<title>[B][COLOR white]BICHO DE SETE CABEÇAS[/COLOR] - [COLOR gold]7.7[/COLOR][/B]</title>
<link>movie=21399.mp4</link>
<info>Duração do filme: 1h, 14min</info>
<genre>Drama</genre>
<date>2001</date>
</item>
<item>
<title>[B][COLOR white]BIG BEAR[/COLOR] - [COLOR gold]5.1[/COLOR][/B]</title>
<link>movie=15072.mp4</link>
<info>Duração do filme: 1h, 27min</info>
<genre>Comédia</genre>
<date>2017</date>
</item>
<item>
<title>[B][COLOR white]BIG BROTHER[/COLOR] - [COLOR gold]6.3[/COLOR][/B]</title>
<link>movie=13991.mp4</link>
<info>Duração do filme: 1h, 51min</info>
<genre>Ação, Drama, Comédia</genre>
<date>2018</date>
</item>
<item>
<title>[B][COLOR white]BIG HOUSE BUNNY[/COLOR] - [COLOR gold]7.5[/COLOR][/B]</title>
<link>movie=26305.mp4</link>
<info>Duração do filme: h, 7min</info>
<genre>Animação, Família, Comédia</genre>
<date>1950</date>
</item>
<item>
<title>[B][COLOR white]BIG JATO[/COLOR] - [COLOR gold]6.7[/COLOR][/B]</title>
<link>movie=22984.mp4</link>
<info>Duração do filme: 1h, 33min</info>
<genre>Drama</genre>
<date>2015</date>
</item>
<item>
<title>[B][COLOR white]BIG KILL - A CIDADE DO MEDO[/COLOR] - [COLOR gold]5.3[/COLOR][/B]</title>
<link>movie=29485.mp4</link>
<info>Duração do filme: 2h, 6min</info>
<genre>Ação, Faroeste</genre>
<date>2019</date>
</item>
<item>
<title>[B][COLOR white]BIG LOVE[/COLOR] - [COLOR gold]5.3[/COLOR][/B]</title>
<link>movie=24991.mp4</link>
<info>Duração do filme: 1h, 40min</info>
<genre>Romance, Suspense</genre>
<date>2012</date>
</item>
<item>
<title>[B][COLOR white]BIG NOTHING[/COLOR] - [COLOR gold]6.8[/COLOR][/B]</title>
<link>movie=17852.mp4</link>
<info>Duração do filme: 1h, 26min</info>
<genre>Ação, Comédia, Crime, Suspense</genre>
<date>2006</date>
</item>
<item>
<title>[B][COLOR white]BIG PAI, BIG FILHO 2[/COLOR][/B]</title>
<link>movie=28070.mp4</link>
<info>Duração do filme: 1h, 29min</info>
<genre>Animação, Aventura, Família</genre>
<date>2020</date>
</item>
<item>
<title>[B][COLOR white]BIG PAI, BIG FILHO[/COLOR] - [COLOR gold]6.1[/COLOR][/B]</title>
<link>movie=21112.mp4</link>
<info>Duração do filme: 1h, 32min</info>
<genre>Animação, Comédia, Família</genre>
<date>2017</date>
</item>
<item>
<title>[B][COLOR white]BIG SHOTS[/COLOR] - [COLOR gold]5.7[/COLOR][/B]</title>
<link>movie=26283.mp4</link>
<info>Duração do filme: 1h, 34min</info>
<genre>Ação, Aventura, Comédia</genre>
<date>1987</date>
</item>
<item>
<title>[B][COLOR white]BIG SKY[/COLOR] - [COLOR gold]4.4[/COLOR][/B]</title>
<link>movie=16258.mp4</link>
<info>Duração do filme: 1h, 35min</info>
<genre>Suspense, Drama</genre>
<date>2015</date>
</item>
<item>
<title>[B][COLOR white]BIG STAN: ARREBENTANDO NA PRISÃO[/COLOR] - [COLOR gold]6.2[/COLOR][/B]</title>
<link>movie=19654.mp4</link>
<info>Duração do filme: 1h, 45min</info>
<genre>Comédia</genre>
<date>2007</date>
</item>
<item>
<title>[B][COLOR white]BIG TIME ADOLESCENCE[/COLOR] - [COLOR gold]7.0[/COLOR][/B]</title>
<link>movie=27050.mp4</link>
<info>Duração do filme: 1h, 31min</info>
<genre>Comédia</genre>
<date>2020</date>
</item>
<item>
<title>[B][COLOR white]BIGFOOT HORROR CAMP[/COLOR] - [COLOR gold]2.2[/COLOR][/B]</title>
<link>movie=22835.mp4</link>
<info>Duração do filme: h, 51min</info>
<genre></genre>
<date>2017</date>
</item>
<item>
<title>[B][COLOR white]BIGFOOT[/COLOR] - [COLOR gold]2.8[/COLOR][/B]</title>
<link>movie=26953.mp4</link>
<info>Duração do filme: 1h, 20min</info>
<genre></genre>
<date>1970</date>
</item>
<item>
<title>[B][COLOR white]BIGGER[/COLOR] - [COLOR gold]6.4[/COLOR][/B]</title>
<link>movie=21053.mp4</link>
<info>Duração do filme: 1h, 47min</info>
<genre>Drama</genre>
<date>2018</date>
</item>
<item>
<title>[B][COLOR white]BIKINI CAR WASH[/COLOR] - [COLOR gold]3.3[/COLOR][/B]</title>
<link>movie=17319.mp4</link>
<info>Duração do filme: 1h, 35min</info>
<genre>Comédia</genre>
<date>2015</date>
</item>
<item>
<title>[B][COLOR white]BIKINI GIRLS V DINOSAURS[/COLOR] - [COLOR gold]2.3[/COLOR][/B]</title>
<link>movie=23231.mp4</link>
<info>Duração do filme: h, 51min</info>
<genre>Comédia, Sci-Fi</genre>
<date>2014</date>
</item>
<item>
<title>[B][COLOR white]BIKINI MODEL ACADEMY[/COLOR] - [COLOR gold]2.1[/COLOR][/B]</title>
<link>movie=17783.mp4</link>
<info>Duração do filme: 1h, 24min</info>
<genre>Comédia</genre>
<date>2015</date>
</item>
<item>
<title>[B][COLOR white]BIKRAM: YOGI, GURU, PREDADOR[/COLOR] - [COLOR gold]6.7[/COLOR][/B]</title>
<link>movie=25797.mp4</link>
<info>Duração do filme: 1h, 26min</info>
<genre>Documentário, Crime</genre>
<date>2019</date>
</item>
<item>
<title>[B][COLOR white]BILHETE DE LOTERIA[/COLOR] - [COLOR gold]5.0[/COLOR][/B]</title>
<link>movie=25654.mp4</link>
<info>Duração do filme: 1h, 39min</info>
<genre>Comédia</genre>
<date>2010</date>
</item>
<item>
<title>[B][COLOR white]BILKO - O SARGENTO TRAPALHÃO[/COLOR] - [COLOR gold]5.9[/COLOR][/B]</title>
<link>movie=15683.mp4</link>
<info>Duração do filme: 1h, 33min</info>
<genre>Comédia, Família</genre>
<date>1996</date>
</item>
<item>
<title>[B][COLOR white]BILL & TED - DOIS LOUCOS NO TEMPO[/COLOR] - [COLOR gold]6.3[/COLOR][/B]</title>
<link>movie=13604.mp4</link>
<info>Duração do filme: 1h, 38min</info>
<genre>Aventura, Comédia, Fantasia, Sci-Fi, Músical</genre>
<date>1991</date>
</item>
<item>
<title>[B][COLOR white]BILL & TED - UMA AVENTURA FANTÁSTICA[/COLOR] - [COLOR gold]6.9[/COLOR][/B]</title>
<link>movie=23753.mp4</link>
<info>Duração do filme: 1h, 30min</info>
<genre>Aventura, Comédia, Sci-Fi</genre>
<date>1989</date>
</item>
<item>
<title>[B][COLOR white]BILL & TED: ENCARE A MÚSICA[/COLOR] - [COLOR gold]6.4[/COLOR][/B]</title>
<link>movie=27334.mp4</link>
<info>Duração do filme: 1h, 32min</info>
<genre>Comédia, Sci-Fi, Aventura</genre>
<date>2020</date>
</item>
<item>
<title>[B][COLOR white]BILL BURR: PAPER TIGER[/COLOR] - [COLOR gold]8.2[/COLOR][/B]</title>
<link>movie=21586.mp4</link>
<info>Duração do filme: 1h, 7min</info>
<genre>Comédia</genre>
<date>2019</date>
</item>
<item>
<title>[B][COLOR white]BILL BURR: WALK YOUR WAY OUT[/COLOR] - [COLOR gold]7.3[/COLOR][/B]</title>
<link>movie=24058.mp4</link>
<info>Duração do filme: 1h, 17min</info>
<genre>Comédia</genre>
<date>2017</date>
</item>
<item>
<title>[B][COLOR white]BILL NYE: SCIENCE GUY[/COLOR] - [COLOR gold]6.0[/COLOR][/B]</title>
<link>movie=19965.mp4</link>
<info>Duração do filme: 1h, 35min</info>
<genre>Documentário</genre>
<date>2017</date>
</item>
<item>
<title>[B][COLOR white]BILLI PIG[/COLOR] - [COLOR gold]3.6[/COLOR][/B]</title>
<link>movie=28021.mp4</link>
<info>Duração do filme: 1h, 51min</info>
<genre>Comédia</genre>
<date>2012</date>
</item>
<item>
<title>[B][COLOR white]BILLIE EILISH: THE WORLD'S A LITTLE BLURRY[/COLOR] - [COLOR gold]7.9[/COLOR][/B]</title>
<link>movie=27757.mp4</link>
<info>Duração do filme: 2h, 20min</info>
<genre>Documentário, Músical</genre>
<date>2021</date>
</item>
<item>
<title>[B][COLOR white]BILLY ELLIOT[/COLOR] - [COLOR gold]7.7[/COLOR][/B]</title>
<link>movie=19378.mp4</link>
<info>Duração do filme: 1h, 50min</info>
<genre>Drama, Comédia, Músical</genre>
<date>2000</date>
</item>
<item>
<title>[B][COLOR white]BILLY MADISON, UM HERDEIRO BOBALHÃO[/COLOR] - [COLOR gold]6.4[/COLOR][/B]</title>
<link>movie=25388.mp4</link>
<info>Duração do filme: 1h, 29min</info>
<genre>Comédia</genre>
<date>1995</date>
</item>
<item>
<title>[B][COLOR white]BILLY STONE E O MEDALHÃO MÁGICO[/COLOR][/B]</title>
<link>movie=28918.mp4</link>
<info>Duração do filme: 1h, 38min</info>
<genre>Aventura, Família</genre>
<date>2013</date>
</item>
<item>
<title>[B][COLOR white]BILLY THE KID[/COLOR] - [COLOR gold]2.3[/COLOR][/B]</title>
<link>movie=16257.mp4</link>
<info>Duração do filme: 1h, 20min</info>
<genre>Ação, Faroeste</genre>
<date>2013</date>
</item>
<item>
<title>[B][COLOR white]BINGO - O REI DAS MANHÃS[/COLOR] - [COLOR gold]8.0[/COLOR][/B]</title>
<link>movie=23120.mp4</link>
<info>Duração do filme: 1h, 53min</info>
<genre>Comédia, Drama</genre>
<date>2017</date>
</item>
<item>
<title>[B][COLOR white]BINGO ESPERTO PRA CACHORRO[/COLOR][/B]</title>
<link>movie=28743.mp4</link>
<info>Duração do filme: 1h, 30min</info>
<genre>Ação, Aventura, Comédia, Família</genre>
<date>1991</date>
</item>
<item>
<title>[B][COLOR white]BIONICLE - A MÁSCARA DA LUZ, O FILME[/COLOR] - [COLOR gold]5.6[/COLOR][/B]</title>
<link>movie=16563.mp4</link>
<info>Duração do filme: 1h, 12min</info>
<genre>Ação, Aventura, Animação, Família, Sci-Fi</genre>
<date>2003</date>
</item>
<item>
<title>[B][COLOR white]BIONICLE 2: LEGENDS OF METRU NUI[/COLOR] - [COLOR gold]6.0[/COLOR][/B]</title>
<link>movie=13250.mp4</link>
<info>Duração do filme: 1h, 12min</info>
<genre>Ação, Família, Animação</genre>
<date>2004</date>
</item>
<item>
<title>[B][COLOR white]BIONICLE: THE LEGEND REBORN[/COLOR] - [COLOR gold]5.2[/COLOR][/B]</title>
<link>movie=16087.mp4</link>
<info>Duração do filme: 1h, 20min</info>
<genre>Ação, Aventura, Animação, Família, Sci-Fi</genre>
<date>2009</date>
</item>
<item>
<title>[B][COLOR white]BIRDEMIC: SHOCK AND TERROR[/COLOR] - [COLOR gold]1.8[/COLOR][/B]</title>
<link>movie=21435.mp4</link>
<info>Duração do filme: 1h, 35min</info>
<genre>Terror, Sci-Fi</genre>
<date>2010</date>
</item>
<item>
<title>[B][COLOR white]BIRDMAN OU (A INESPERADA VIRTUDE DA IGNORÂNCIA)[/COLOR] - [COLOR gold]7.7[/COLOR][/B]</title>
<link>movie=14750.mp4</link>
<info>Duração do filme: 1h, 59min</info>
<genre>Drama, Comédia</genre>
<date>2014</date>
</item>
<item>
<title>[B][COLOR white]BIRDSHOT[/COLOR] - [COLOR gold]6.6[/COLOR][/B]</title>
<link>movie=15616.mp4</link>
<info>Duração do filme: 1h, 56min</info>
<genre>Suspense, Drama, Mistério</genre>
<date>2017</date>
</item>
<item>
<title>[B][COLOR white]BIRLESEN GÖNÜLLER[/COLOR] - [COLOR gold]7.7[/COLOR][/B]</title>
<link>movie=29842.mp4</link>
<info>Duração do filme: 2h, 6min</info>
<genre>História, Drama</genre>
<date>2014</date>
</item>
<item>
<title>[B][COLOR white]BISHOUJO SENSHI SAILOR MOON S: HEARTS IN ICE[/COLOR] - [COLOR gold]7.7[/COLOR][/B]</title>
<link>movie=20401.mp4</link>
<info>Duração do filme: 1h, 0min</info>
<genre>Animação, Ação, Comédia</genre>
<date>1994</date>
</item>
<item>
<title>[B][COLOR white]BIT[/COLOR] - [COLOR gold]4.1[/COLOR][/B]</title>
<link>movie=27696.mp4</link>
<info>Duração do filme: 1h, 30min</info>
<genre>Terror, Comédia</genre>
<date>2019</date>
</item>
<item>
<title>[B][COLOR white]BITCH[/COLOR] - [COLOR gold]5.1[/COLOR][/B]</title>
<link>movie=18784.mp4</link>
<info>Duração do filme: 1h, 33min</info>
<genre>Família, Comédia, Drama, Suspense</genre>
<date>2017</date>
</item>
<item>
<title>[B][COLOR white]BITE[/COLOR] - [COLOR gold]4.9[/COLOR][/B]</title>
<link>movie=17217.mp4</link>
<info>Duração do filme: 1h, 30min</info>
<genre>Terror</genre>
<date>2015</date>
</item>
<item>
<title>[B][COLOR white]BITTER MELON[/COLOR] - [COLOR gold]6.3[/COLOR][/B]</title>
<link>movie=20009.mp4</link>
<info>Duração do filme: 1h, 20min</info>
<genre>Comédia, Crime</genre>
<date>2018</date>
</item>
<item>
<title>[B][COLOR white]BIUTIFUL[/COLOR] - [COLOR gold]7.5[/COLOR][/B]</title>
<link>movie=22505.mp4</link>
<info>Duração do filme: 2h, 27min</info>
<genre>Drama</genre>
<date>2010</date>
</item>
<item>
<title>[B][COLOR white]BIZARRE[/COLOR] - [COLOR gold]4.6[/COLOR][/B]</title>
<link>movie=20498.mp4</link>
<info>Duração do filme: 1h, 39min</info>
<genre>Drama, Romance</genre>
<date>2015</date>
</item>
<item>
<title>[B][COLOR white]BLACK '47[/COLOR] - [COLOR gold]6.8[/COLOR][/B]</title>
<link>movie=22504.mp4</link>
<info>Duração do filme: 1h, 40min</info>
<genre>Drama, Faroeste</genre>
<date>2018</date>
</item>
<item>
<title>[B][COLOR white]BLACK ART: IN THE ABSENCE OF LIGHT[/COLOR] - [COLOR gold]6.3[/COLOR][/B]</title>
<link>movie=27734.mp4</link>
<info>Duração do filme: 1h, 25min</info>
<genre>Documentário</genre>
<date>2021</date>
</item>
<item>
<title>[B][COLOR white]BLACK BEAR[/COLOR] - [COLOR gold]6.6[/COLOR][/B]</title>
<link>movie=27643.mp4</link>
<info>Duração do filme: 1h, 45min</info>
<genre>Drama, Comédia, Suspense</genre>
<date>2020</date>
</item>
<item>
<title>[B][COLOR white]BLACK CADILLAC[/COLOR] - [COLOR gold]5.9[/COLOR][/B]</title>
<link>movie=28317.mp4</link>
<info>Duração do filme: 1h, 33min</info>
<genre>Drama, Suspense</genre>
<date>2003</date>
</item>
<item>
<title>[B][COLOR white]BLACK DAY BLUE NIGHT[/COLOR] - [COLOR gold]5.9[/COLOR][/B]</title>
<link>movie=20706.mp4</link>
<info>Duração do filme: 1h, 33min</info>
<genre>Drama, Suspense, Crime, Romance</genre>
<date>1995</date>
</item>
<item>
<title>[B][COLOR white]BLACK DOG - ESTRADA ALUCINANTE[/COLOR] - [COLOR gold]5.5[/COLOR][/B]</title>
<link>movie=18975.mp4</link>
<info>Duração do filme: 1h, 28min</info>
<genre>Ação, Suspense, Crime, Drama</genre>
<date>1998</date>
</item>
<item>
<title>[B][COLOR white]BLACK DYNAMITE[/COLOR] - [COLOR gold]7.4[/COLOR][/B]</title>
<link>movie=16308.mp4</link>
<info>Duração do filme: 1h, 24min</info>
<genre>Ação, Comédia</genre>
<date>2009</date>
</item>
<item>
<title>[B][COLOR white]BLACK IS KING[/COLOR] - [COLOR gold]6.6[/COLOR][/B]</title>
<link>movie=27242.mp4</link>
<info>Duração do filme: 1h, 26min</info>
<genre>Músical</genre>
<date>2020</date>
</item>
<item>
<title>[B][COLOR white]BLACK JACK: O FILME[/COLOR] - [COLOR gold]6.8[/COLOR][/B]</title>
<link>movie=21040.mp4</link>
<info>Duração do filme: 1h, 33min</info>
<genre>Animação, Drama, Suspense</genre>
<date>1996</date>
</item>
<item>
<title>[B][COLOR white]BLACK MIRROR - BANDERSNATCH[/COLOR] - [COLOR gold]7.2[/COLOR][/B]</title>
<link>movie=17856.mp4</link>
<info>Duração do filme: 1h, 30min</info>
<genre>Sci-Fi, Mistério, Drama, Suspense, tv movie</genre>
<date>2018</date>
</item>
<item>
<title>[B][COLOR white]BLACK NATIVITY[/COLOR] - [COLOR gold]4.5[/COLOR][/B]</title>
<link>movie=14477.mp4</link>
<info>Duração do filme: 1h, 33min</info>
<genre>Drama, Músical</genre>
<date>2013</date>
</item>
<item>
<title>[B][COLOR white]BLACK SHEEP[/COLOR] - [COLOR gold]5.8[/COLOR][/B]</title>
<link>movie=23144.mp4</link>
<info>Duração do filme: 1h, 27min</info>
<genre>Terror, Comédia</genre>
<date>2006</date>
</item>
<item>
<title>[B][COLOR white]BLACK SITE DELTA[/COLOR] - [COLOR gold]3.8[/COLOR][/B]</title>
<link>movie=16330.mp4</link>
<info>Duração do filme: 1h, 27min</info>
<genre>Ação</genre>
<date>2017</date>
</item>
<item>
<title>[B][COLOR white]BLACK WATER: ABYSS[/COLOR] - [COLOR gold]4.6[/COLOR][/B]</title>
<link>movie=27262.mp4</link>
<info>Duração do filme: 1h, 38min</info>
<genre>Terror, Suspense, Aventura</genre>
<date>2020</date>
</item>
<item>
<title>[B][COLOR white]BLACKBIRD[/COLOR] - [COLOR gold]5.5[/COLOR][/B]</title>
<link>movie=24452.mp4</link>
<info>Duração do filme: 1h, 39min</info>
<genre>Drama</genre>
<date>2014</date>
</item>
<item>
<title>[B][COLOR white]BLACKBIRD[/COLOR] - [COLOR gold]6.3[/COLOR][/B]</title>
<link>movie=27454.mp4</link>
<info>Duração do filme: 1h, 38min</info>
<genre>Drama</genre>
<date>2020</date>
</item>
<item>
<title>[B][COLOR white]BLACKFISH – FÚRIA ANIMAL[/COLOR] - [COLOR gold]8.1[/COLOR][/B]</title>
<link>movie=17152.mp4</link>
<info>Duração do filme: 1h, 23min</info>
<genre>Documentário</genre>
<date>2013</date>
</item>
<item>
<title>[B][COLOR white]BLACKPINK: LIGHT UP THE SKY[/COLOR] - [COLOR gold]7.7[/COLOR][/B]</title>
<link>movie=27441.mp4</link>
<info>Duração do filme: 1h, 19min</info>
<genre>Documentário, Músical</genre>
<date>2020</date>
</item>
<item>
<title>[B][COLOR white]BLADE - O CAÇADOR DE VAMPIROS[/COLOR] - [COLOR gold]7.1[/COLOR][/B]</title>
<link>movie=23559.mp4</link>
<info>Duração do filme: 2h, 0min</info>
<genre>Terror, Ação</genre>
<date>1998</date>
</item>
<item>
<title>[B][COLOR white]BLADE II - O CAÇADOR DE VAMPIROS[/COLOR] - [COLOR gold]6.7[/COLOR][/B]</title>
<link>movie=23935.mp4</link>
<info>Duração do filme: 1h, 57min</info>
<genre>Fantasia, Terror, Ação, Suspense</genre>
<date>2002</date>
</item>
<item>
<title>[B][COLOR white]BLADE RUNNER 2049[/COLOR] - [COLOR gold]8.0[/COLOR][/B]</title>
<link>movie=23200.mp4</link>
<info>Duração do filme: 2h, 44min</info>
<genre>Sci-Fi, Drama</genre>
<date>2017</date>
</item>
<item>
<title>[B][COLOR white]BLADE RUNNER: O CAÇADOR DE ANDRÓIDES[/COLOR] - [COLOR gold]8.1[/COLOR][/B]</title>
<link>movie=17727.mp4</link>
<info>Duração do filme: 1h, 57min</info>
<genre>Sci-Fi, Drama, Suspense</genre>
<date>1982</date>
</item>
<item>
<title>[B][COLOR white]BLADE: TRINITY[/COLOR] - [COLOR gold]5.9[/COLOR][/B]</title>
<link>movie=23456.mp4</link>
<info>Duração do filme: 1h, 53min</info>
<genre>Sci-Fi, Ação, Terror, Suspense, Aventura, Fantasia</genre>
<date>2004</date>
</item>
<item>
<title>[B][COLOR white]BLAME![/COLOR] - [COLOR gold]6.7[/COLOR][/B]</title>
<link>movie=16714.mp4</link>
<info>Duração do filme: 1h, 46min</info>
<genre>Ação, Drama, Sci-Fi, Animação</genre>
<date>2017</date>
</item>
<item>
<title>[B][COLOR white]BLAME[/COLOR] - [COLOR gold]5.8[/COLOR][/B]</title>
<link>movie=21524.mp4</link>
<info>Duração do filme: 1h, 40min</info>
<genre>Drama</genre>
<date>2018</date>
</item>
<item>
<title>[B][COLOR white]BLANK[/COLOR] - [COLOR gold]6.2[/COLOR][/B]</title>
<link>movie=25969.mp4</link>
<info>Duração do filme: 1h, 51min</info>
<genre>Ação, Suspense</genre>
<date>2019</date>
</item>
<item>
<title>[B][COLOR white]BLAZE[/COLOR] - [COLOR gold]6.6[/COLOR][/B]</title>
<link>movie=19051.mp4</link>
<info>Duração do filme: 2h, 9min</info>
<genre>Drama, Músical, História</genre>
<date>2018</date>
</item>
<item>
<title>[B][COLOR white]BLEACH: 1 - MEMORIES OF NOBODY[/COLOR] - [COLOR gold]7.2[/COLOR][/B]</title>
<link>movie=20047.mp4</link>
<info>Duração do filme: 1h, 30min</info>
<genre>Fantasia, Animação, Sci-Fi</genre>
<date>2006</date>
</item>
<item>
<title>[B][COLOR white]BLEACH: 2 - THE DIAMOND DUST REBELLION[/COLOR] - [COLOR gold]7.1[/COLOR][/B]</title>
<link>movie=13230.mp4</link>
<info>Duração do filme: 1h, 32min</info>
<genre>Ação, Aventura, Animação</genre>
<date>2007</date>
</item>
<item>
<title>[B][COLOR white]BLEACH: 3 - FADE TO BLACK[/COLOR] - [COLOR gold]7.3[/COLOR][/B]</title>
<link>movie=15321.mp4</link>
<info>Duração do filme: 1h, 34min</info>
<genre>Ação, Comédia, Animação</genre>
<date>2008</date>
</item>
<item>
<title>[B][COLOR white]BLEACH: 4 - JIGOKU-HEN[/COLOR] - [COLOR gold]7.4[/COLOR][/B]</title>
<link>movie=18779.mp4</link>
<info>Duração do filme: 1h, 33min</info>
<genre>Ação, Comédia, Animação</genre>
<date>2010</date>
</item>
<item>
<title>[B][COLOR white]BLEACH[/COLOR] - [COLOR gold]6.4[/COLOR][/B]</title>
<link>movie=22389.mp4</link>
<info>Duração do filme: 1h, 48min</info>
<genre>Ação, Fantasia, Aventura</genre>
<date>2018</date>
</item>
<item>
<title>[B][COLOR white]BLIND – EU ESTOU AQUI[/COLOR] - [COLOR gold]4.6[/COLOR][/B]</title>
<link>movie=27560.mp4</link>
<info>Duração do filme: 1h, 30min</info>
<genre>Drama, Terror</genre>
<date>2019</date>
</item>
<item>
<title>[B][COLOR white]BLIND[/COLOR] - [COLOR gold]6.9[/COLOR][/B]</title>
<link>movie=15459.mp4</link>
<info>Duração do filme: 1h, 36min</info>
<genre>Drama</genre>
<date>2014</date>
</item>
<item>
<title>[B][COLOR white]BLING RING: A GANGUE DE HOLLYWOOD[/COLOR] - [COLOR gold]5.6[/COLOR][/B]</title>
<link>movie=14085.mp4</link>
<info>Duração do filme: 1h, 30min</info>
<genre>Drama, Crime</genre>
<date>2013</date>
</item>
<item>
<title>[B][COLOR white]BLING[/COLOR] - [COLOR gold]4.5[/COLOR][/B]</title>
<link>movie=23677.mp4</link>
<info>Duração do filme: 1h, 21min</info>
<genre>Família</genre>
<date>2016</date>
</item>
<item>
<title>[B][COLOR white]BLISS: EM BUSCA DA FELICIDADE[/COLOR] - [COLOR gold]4.9[/COLOR][/B]</title>
<link>movie=27692.mp4</link>
<info>Duração do filme: 1h, 43min</info>
<genre>Sci-Fi, Drama, Romance</genre>
<date>2021</date>
</item>
<item>
<title>[B][COLOR white]BLISS[/COLOR] - [COLOR gold]5.8[/COLOR][/B]</title>
<link>movie=18798.mp4</link>
<info>Duração do filme: 1h, 20min</info>
<genre>Terror</genre>
<date>2019</date>
</item>
<item>
<title>[B][COLOR white]BLITZ[/COLOR] - [COLOR gold]6.2[/COLOR][/B]</title>
<link>movie=20016.mp4</link>
<info>Duração do filme: 1h, 37min</info>
<genre>Crime, Ação, Suspense</genre>
<date>2011</date>
</item>
<item>
<title>[B][COLOR white]BLOCKBUSTER[/COLOR] - [COLOR gold]5.6[/COLOR][/B]</title>
<link>movie=21906.mp4</link>
<info>Duração do filme: 1h, 25min</info>
<genre>Comédia</genre>
<date>2017</date>
</item>
<item>
<title>[B][COLOR white]BLOOD-C THE LAST DARK[/COLOR] - [COLOR gold]6.1[/COLOR][/B]</title>
<link>movie=21416.mp4</link>
<info>Duração do filme: 1h, 46min</info>
<genre>Ação, Terror, Sci-Fi, Animação</genre>
<date>2012</date>
</item>
<item>
<title>[B][COLOR white]BLOOD CREEK[/COLOR] - [COLOR gold]5.3[/COLOR][/B]</title>
<link>movie=26372.mp4</link>
<info>Duração do filme: 1h, 30min</info>
<genre>Terror, Suspense</genre>
<date>2009</date>
</item>
<item>
<title>[B][COLOR white]BLOOD FEST[/COLOR] - [COLOR gold]5.3[/COLOR][/B]</title>
<link>movie=16984.mp4</link>
<info>Duração do filme: 1h, 33min</info>
<genre>Comédia, Terror</genre>
<date>2018</date>
</item>
<item>
<title>[B][COLOR white]BLOOD HUNT[/COLOR] - [COLOR gold]4.5[/COLOR][/B]</title>
<link>movie=25674.mp4</link>
<info>Duração do filme: 1h, 17min</info>
<genre>Suspense, Terror</genre>
<date>2016</date>
</item>
<item>
<title>[B][COLOR white]BLOOD LAKE: ATTACK OF THE KILLER LAMPREYS[/COLOR] - [COLOR gold]3.8[/COLOR][/B]</title>
<link>movie=24689.mp4</link>
<info>Duração do filme: 1h, 30min</info>
<genre>Terror, Comédia</genre>
<date>2014</date>
</item>
<item>
<title>[B][COLOR white]BLOOD MONEY[/COLOR] - [COLOR gold]5.7[/COLOR][/B]</title>
<link>movie=17336.mp4</link>
<info>Duração do filme: 1h, 18min</info>
<genre>Suspense, Terror</genre>
<date>2017</date>
</item>
<item>
<title>[B][COLOR white]BLOOD ON HER NAME[/COLOR] - [COLOR gold]5.5[/COLOR][/B]</title>
<link>movie=27296.mp4</link>
<info>Duração do filme: 1h, 25min</info>
<genre>Drama, Suspense, Crime</genre>
<date>2020</date>
</item>
<item>
<title>[B][COLOR white]BLOOD ORANGE[/COLOR] - [COLOR gold]4.3[/COLOR][/B]</title>
<link>movie=16926.mp4</link>
<info>Duração do filme: 1h, 25min</info>
<genre>Suspense</genre>
<date>2016</date>
</item>
<item>
<title>[B][COLOR white]BLOOD QUANTUM[/COLOR] - [COLOR gold]5.5[/COLOR][/B]</title>
<link>movie=27029.mp4</link>
<info>Duração do filme: 1h, 36min</info>
<genre>Terror</genre>
<date>2019</date>
</item>
<item>
<title>[B][COLOR white]BLOOD ROAD[/COLOR] - [COLOR gold]6.7[/COLOR][/B]</title>
<link>movie=25158.mp4</link>
<info>Duração do filme: 1h, 36min</info>
<genre>Documentário</genre>
<date>2017</date>
</item>
<item>
<title>[B][COLOR white]BLOOD TRAP[/COLOR] - [COLOR gold]3.8[/COLOR][/B]</title>
<link>movie=24685.mp4</link>
<info>Duração do filme: 1h, 30min</info>
<genre>Ação, Crime, Suspense, Terror</genre>
<date>2016</date>
</item>
<item>
<title>[B][COLOR white]BLOOD TYPE[/COLOR][/B]</title>
<link>movie=28766.mp4</link>
<info>Duração do filme: 1h, 18min</info>
<genre>Mistério, Drama, Comédia</genre>
<date>2018</date>
</item>
<item>
<title>[B][COLOR white]BLOOD VESSEL[/COLOR] - [COLOR gold]5.2[/COLOR][/B]</title>
<link>movie=27297.mp4</link>
<info>Duração do filme: 1h, 33min</info>
<genre>Terror, Sci-Fi</genre>
<date>2019</date>
</item>
<item>
<title>[B][COLOR white]BLOOD: THE LAST VAMPIRE[/COLOR] - [COLOR gold]6.7[/COLOR][/B]</title>
<link>movie=22010.mp4</link>
<info>Duração do filme: h, 48min</info>
<genre>Fantasia, Animação, Terror, Comédia, Suspense, Sci-Fi</genre>
<date>2000</date>
</item>
<item>
<title>[B][COLOR white]BLOODLINE[/COLOR] - [COLOR gold]6.0[/COLOR][/B]</title>
<link>movie=21730.mp4</link>
<info>Duração do filme: 1h, 35min</info>
<genre>Suspense, Crime</genre>
<date>2019</date>
</item>
<item>
<title>[B][COLOR white]BLOODRAYNE 2 - LIBERTAÇÃO[/COLOR] - [COLOR gold]2.6[/COLOR][/B]</title>
<link>movie=18263.mp4</link>
<info>Duração do filme: 1h, 39min</info>
<genre>Ação, Terror, Faroeste</genre>
<date>2007</date>
</item>
<item>
<title>[B][COLOR white]BLOODRAYNE 3 – O TERCEIRO REICH[/COLOR] - [COLOR gold]3.0[/COLOR][/B]</title>
<link>movie=17236.mp4</link>
<info>Duração do filme: 1h, 19min</info>
<genre>Ação, Aventura, Fantasia, Terror</genre>
<date>2010</date>
</item>
<item>
<title>[B][COLOR white]BLOODRAYNE[/COLOR] - [COLOR gold]2.9[/COLOR][/B]</title>
<link>movie=16204.mp4</link>
<info>Duração do filme: 1h, 35min</info>
<genre>Ação, Aventura, Fantasia, Terror</genre>
<date>2005</date>
</item>
<item>
<title>[B][COLOR white]BLOODRUNNERS[/COLOR] - [COLOR gold]4.9[/COLOR][/B]</title>
<link>movie=21728.mp4</link>
<info>Duração do filme: 1h, 40min</info>
<genre>Crime, Terror</genre>
<date>2017</date>
</item>
<item>
<title>[B][COLOR white]BLOODSHOT[/COLOR] - [COLOR gold]5.7[/COLOR][/B]</title>
<link>movie=26731.mp4</link>
<info>Duração do filme: 1h, 50min</info>
<genre>Ação, Drama, Fantasia, Sci-Fi</genre>
<date>2020</date>
</item>
<item>
<title>[B][COLOR white]BLOODSUCKING BASTARDS[/COLOR] - [COLOR gold]5.7[/COLOR][/B]</title>
<link>movie=25338.mp4</link>
<info>Duração do filme: 1h, 24min</info>
<genre>Comédia, Terror</genre>
<date>2015</date>
</item>
<item>
<title>[B][COLOR white]BLOOMINGTON[/COLOR] - [COLOR gold]5.9[/COLOR][/B]</title>
<link>movie=25519.mp4</link>
<info>Duração do filme: 1h, 23min</info>
<genre>Drama, Romance, Lgbt</genre>
<date>2010</date>
</item>
<item>
<title>[B][COLOR white]BLOW-UP: DEPOIS DAQUELE BEIJO[/COLOR] - [COLOR gold]7.6[/COLOR][/B]</title>
<link>movie=15822.mp4</link>
<info>Duração do filme: 1h, 51min</info>
<genre>Drama, Mistério, Suspense</genre>
<date>1966</date>
</item>
<item>
<title>[B][COLOR white]BLOWTORCH[/COLOR] - [COLOR gold]4.2[/COLOR][/B]</title>
<link>movie=14711.mp4</link>
<info>Duração do filme: 1h, 20min</info>
<genre>Suspense, Crime, Drama</genre>
<date>2016</date>
</item>
<item>
<title>[B][COLOR white]BLUE BIRD[/COLOR] - [COLOR gold]6.0[/COLOR][/B]</title>
<link>movie=14305.mp4</link>
<info>Duração do filme: 1h, 26min</info>
<genre>Drama</genre>
<date>2011</date>
</item>
<item>
<title>[B][COLOR white]BLUE CAR[/COLOR] - [COLOR gold]6.5[/COLOR][/B]</title>
<link>movie=25051.mp4</link>
<info>Duração do filme: 1h, 32min</info>
<genre>Drama</genre>
<date>2003</date>
</item>
<item>
<title>[B][COLOR white]BLUE GENDER: THE WARRIOR[/COLOR] - [COLOR gold]5.6[/COLOR][/B]</title>
<link>movie=13571.mp4</link>
<info>Duração do filme: 1h, 30min</info>
<genre>Animação, Sci-Fi</genre>
<date>2002</date>
</item>
<item>
<title>[B][COLOR white]BLUE ICE[/COLOR] - [COLOR gold]5.2[/COLOR][/B]</title>
<link>movie=21372.mp4</link>
<info>Duração do filme: 1h, 45min</info>
<genre>Ação, Suspense</genre>
<date>1992</date>
</item>
<item>
<title>[B][COLOR white]BLUE IGUANA[/COLOR] - [COLOR gold]5.5[/COLOR][/B]</title>
<link>movie=13364.mp4</link>
<info>Duração do filme: 1h, 40min</info>
<genre>Suspense, Romance, Comédia, Ação</genre>
<date>2018</date>
</item>
<item>
<title>[B][COLOR white]BLUE JASMINE[/COLOR] - [COLOR gold]7.3[/COLOR][/B]</title>
<link>movie=20848.mp4</link>
<info>Duração do filme: 1h, 38min</info>
<genre>Comédia, Drama</genre>
<date>2013</date>
</item>
<item>
<title>[B][COLOR white]BLUE JAY[/COLOR] - [COLOR gold]7.3[/COLOR][/B]</title>
<link>movie=15329.mp4</link>
<info>Duração do filme: 1h, 25min</info>
<genre>Drama</genre>
<date>2016</date>
</item>
<item>
<title>[B][COLOR white]BLUE MOUNTAIN STATE: THE RISE OF THADLAND[/COLOR] - [COLOR gold]5.8[/COLOR][/B]</title>
<link>movie=23003.mp4</link>
<info>Duração do filme: 1h, 30min</info>
<genre>Comédia</genre>
<date>2016</date>
</item>
<item>
<title>[B][COLOR white]BLUE MY MIND[/COLOR] - [COLOR gold]6.1[/COLOR][/B]</title>
<link>movie=16779.mp4</link>
<info>Duração do filme: 1h, 37min</info>
<genre>Fantasia, Drama</genre>
<date>2018</date>
</item>
<item>
<title>[B][COLOR white]BLUE SEDUCTION[/COLOR] - [COLOR gold]3.8[/COLOR][/B]</title>
<link>movie=22541.mp4</link>
<info>Duração do filme: 1h, 31min</info>
<genre>Suspense, Romance</genre>
<date>2009</date>
</item>
<item>
<title>[B][COLOR white]BLURRED LINES: INSIDE THE ART WORLD[/COLOR] - [COLOR gold]6.3[/COLOR][/B]</title>
<link>movie=24372.mp4</link>
<info>Duração do filme: 1h, 24min</info>
<genre>Documentário</genre>
<date>2017</date>
</item>
<item>
<title>[B][COLOR white]BO BURNHAM: INSIDE[/COLOR] - [COLOR gold]8.9[/COLOR][/B]</title>
<link>movie=29754.mp4</link>
<info>Duração do filme: 1h, 27min</info>
<genre>Comédia</genre>
<date>2021</date>
</item>
<item>
<title>[B][COLOR white]BOA NOITE E BOA SORTE[/COLOR] - [COLOR gold]7.4[/COLOR][/B]</title>
<link>movie=17959.mp4</link>
<info>Duração do filme: 1h, 33min</info>
<genre>Drama, História</genre>
<date>2005</date>
</item>
<item>
<title>[B][COLOR white]BOA NOITE, MAMÃE[/COLOR] - [COLOR gold]6.7[/COLOR][/B]</title>
<link>movie=21309.mp4</link>
<info>Duração do filme: 1h, 39min</info>
<genre>Drama, Terror, Suspense</genre>
<date>2014</date>
</item>
<item>
<title>[B][COLOR white]BOA SORTE[/COLOR] - [COLOR gold]6.7[/COLOR][/B]</title>
<link>movie=24916.mp4</link>
<info>Duração do filme: 1h, 30min</info>
<genre>Drama</genre>
<date>2014</date>
</item>
<item>
<title>[B][COLOR white]BOA VS. PYTHON: AS PREDADORAS[/COLOR][/B]</title>
<link>movie=28518.mp4</link>
<info>Duração do filme: 1h, 32min</info>
<genre>Terror, Sci-Fi</genre>
<date>2004</date>
</item>
<item>
<title>[B][COLOR white]BOAS INTENÇÕES[/COLOR] - [COLOR gold]5.7[/COLOR][/B]</title>
<link>movie=27397.mp4</link>
<info>Duração do filme: 1h, 43min</info>
<genre>Drama, Comédia</genre>
<date>2018</date>
</item>
<item>
<title>[B][COLOR white]BOB ESPONJA - O FILME[/COLOR] - [COLOR gold]7.1[/COLOR][/B]</title>
<link>movie=14431.mp4</link>
<info>Duração do filme: 1h, 22min</info>
<genre>Animação, Comédia, Família</genre>
<date>2004</date>
</item>
<item>
<title>[B][COLOR white]BOB ESPONJA - UM HERÓI FORA D'ÁGUA[/COLOR] - [COLOR gold]6.0[/COLOR][/B]</title>
<link>movie=23061.mp4</link>
<info>Duração do filme: 1h, 33min</info>
<genre>Aventura, Comédia, Família, Fantasia, Animação</genre>
<date>2015</date>
</item>
<item>
<title>[B][COLOR white]BOB ESPONJA: O INCRÍVEL RESGATE[/COLOR] - [COLOR gold]6.2[/COLOR][/B]</title>
<link>movie=27476.mp4</link>
<info>Duração do filme: 1h, 31min</info>
<genre>Fantasia, Animação, Aventura, Comédia, Família</genre>
<date>2020</date>
</item>
<item>
<title>[B][COLOR white]BOB LAZAR: ÁREA 51 E OS DISCOS VOADORES[/COLOR] - [COLOR gold]5.5[/COLOR][/B]</title>
<link>movie=16082.mp4</link>
<info>Duração do filme: 1h, 37min</info>
<genre>Documentário</genre>
<date>2018</date>
</item>
<item>
<title>[B][COLOR white]BOB ROSS ALEGRIA TRAIÇÃO E GANÂNCIA[/COLOR] - [COLOR gold]7.1[/COLOR][/B]</title>
<link>movie=29976.mp4</link>
<info>Duração do filme: 1h, 32min</info>
<genre>Documentário</genre>
<date>2021</date>
</item>
<item>
<title>[B][COLOR white]BOB RUBIN: ODDITIES AND RARITIES[/COLOR] - [COLOR gold]5.1[/COLOR][/B]</title>
<link>movie=27077.mp4</link>
<info>Duração do filme: 1h, 20min</info>
<genre>Comédia</genre>
<date>2020</date>
</item>
<item>
<title>[B][COLOR white]BOBBY ROBSON: MORE THAN A MANAGER[/COLOR] - [COLOR gold]8.2[/COLOR][/B]</title>
<link>movie=29920.mp4</link>
<info>Duração do filme: 1h, 44min</info>
<genre>Documentário</genre>
<date>2018</date>
</item>
<item>
<title>[B][COLOR white]BOBBY[/COLOR] - [COLOR gold]7.0[/COLOR][/B]</title>
<link>movie=25195.mp4</link>
<info>Duração do filme: 2h, 0min</info>
<genre>Drama</genre>
<date>2006</date>
</item>
<item>
<title>[B][COLOR white]BOCA DO LIXO[/COLOR] - [COLOR gold]5.6[/COLOR][/B]</title>
<link>movie=29145.mp4</link>
<info>Duração do filme: 1h, 40min</info>
<genre>Ação, Crime, Drama</genre>
<date>2010</date>
</item>
<item>
<title>[B][COLOR white]BODIED[/COLOR] - [COLOR gold]7.1[/COLOR][/B]</title>
<link>movie=21239.mp4</link>
<info>Duração do filme: 2h, 0min</info>
<genre>Drama, Comédia</genre>
<date>2018</date>
</item>
<item>
<title>[B][COLOR white]BODOM[/COLOR] - [COLOR gold]5.2[/COLOR][/B]</title>
<link>movie=21912.mp4</link>
<info>Duração do filme: 1h, 30min</info>
<genre>Terror</genre>
<date>2016</date>
</item>
<item>
<title>[B][COLOR white]BODY CAM[/COLOR] - [COLOR gold]5.2[/COLOR][/B]</title>
<link>movie=27080.mp4</link>
<info>Duração do filme: 1h, 36min</info>
<genre>Suspense, Terror, Mistério</genre>
<date>2020</date>
</item>
<item>
<title>[B][COLOR white]BODY OF SIN[/COLOR] - [COLOR gold]5.7[/COLOR][/B]</title>
<link>movie=29238.mp4</link>
<info>Duração do filme: 1h, 24min</info>
<genre>Crime, Suspense</genre>
<date>2018</date>
</item>
<item>
<title>[B][COLOR white]BOÊMIO ENCANTADOR[/COLOR] - [COLOR gold]7.8[/COLOR][/B]</title>
<link>movie=20726.mp4</link>
<info>Duração do filme: 1h, 37min</info>
<genre>Comédia, Romance</genre>
<date>1938</date>
</item>
<item>
<title>[B][COLOR white]BOHEMIAN RHAPSODY[/COLOR] - [COLOR gold]8.0[/COLOR][/B]</title>
<link>movie=24461.mp4</link>
<info>Duração do filme: 2h, 15min</info>
<genre>Drama, Músical</genre>
<date>2018</date>
</item>
<item>
<title>[B][COLOR white]BOI NEON[/COLOR][/B]</title>
<link>movie=28830.mp4</link>
<info>Duração do filme: 1h, 41min</info>
<genre>Drama</genre>
<date>2016</date>
</item>
<item>
<title>[B][COLOR white]BOI[/COLOR] - [COLOR gold]4.8[/COLOR][/B]</title>
<link>movie=21312.mp4</link>
<info>Duração do filme: 1h, 51min</info>
<genre>Suspense</genre>
<date>2019</date>
</item>
<item>
<title>[B][COLOR white]BOKEH[/COLOR] - [COLOR gold]5.0[/COLOR][/B]</title>
<link>movie=21206.mp4</link>
<info>Duração do filme: 1h, 44min</info>
<genre>Drama, Sci-Fi, Suspense</genre>
<date>2017</date>
</item>
<item>
<title>[B][COLOR white]BOKU WA ASHITA, KINOU NO KIMI TO DATE SURU[/COLOR] - [COLOR gold]7.5[/COLOR][/B]</title>
<link>movie=24831.mp4</link>
<info>Duração do filme: 1h, 51min</info>
<genre>Romance, Drama</genre>
<date>2016</date>
</item>
<item>
<title>[B][COLOR white]BOLDEN - A SENSAÇÃO DO JAZZ[/COLOR] - [COLOR gold]5.6[/COLOR][/B]</title>
<link>movie=14691.mp4</link>
<info>Duração do filme: 1h, 48min</info>
<genre>Drama, Músical</genre>
<date>2019</date>
</item>
<item>
<title>[B][COLOR white]BOLERO - UMA AVENTURA EM ÊXTASE[/COLOR] - [COLOR gold]3.0[/COLOR][/B]</title>
<link>movie=21797.mp4</link>
<info>Duração do filme: 1h, 45min</info>
<genre>Drama, Romance</genre>
<date>1984</date>
</item>
<item>
<title>[B][COLOR white]BOLES[/COLOR] - [COLOR gold]7.0[/COLOR][/B]</title>
<link>movie=21228.mp4</link>
<info>Duração do filme: h, 13min</info>
<genre>Animação, Comédia</genre>
<date>2013</date>
</item>
<item>
<title>[B][COLOR white]BOLT - SUPERCÃO[/COLOR] - [COLOR gold]6.8[/COLOR][/B]</title>
<link>movie=14032.mp4</link>
<info>Duração do filme: 1h, 38min</info>
<genre>Animação, Família, Aventura, Comédia</genre>
<date>2008</date>
</item>
<item>
<title>[B][COLOR white]BOM COMPORTAMENTO[/COLOR] - [COLOR gold]7.4[/COLOR][/B]</title>
<link>movie=19303.mp4</link>
<info>Duração do filme: 1h, 42min</info>
<genre>Crime, Drama, Suspense</genre>
<date>2017</date>
</item>
<item>
<title>[B][COLOR white]BOM DIA, VIETNÃ[/COLOR] - [COLOR gold]7.3[/COLOR][/B]</title>
<link>movie=17149.mp4</link>
<info>Duração do filme: 2h, 1min</info>
<genre>Comédia, Drama, Guerra</genre>
<date>1987</date>
</item>
<item>
<title>[B][COLOR white]BOM POLÍCIA, MAU POLÍCIA[/COLOR] - [COLOR gold]6.8[/COLOR][/B]</title>
<link>movie=18801.mp4</link>
<info>Duração do filme: 1h, 56min</info>
<genre>Ação, Comédia, Crime</genre>
<date>2006</date>
</item>
<item>
<title>[B][COLOR white]BOMB CITY[/COLOR] - [COLOR gold]6.8[/COLOR][/B]</title>
<link>movie=15618.mp4</link>
<info>Duração do filme: 1h, 35min</info>
<genre>Drama, Crime</genre>
<date>2017</date>
</item>
<item>
<title>[B][COLOR white]BOMBAY ROSE[/COLOR] - [COLOR gold]5.9[/COLOR][/B]</title>
<link>movie=27780.mp4</link>
<info>Duração do filme: 1h, 33min</info>
<genre>Animação, Drama, Romance</genre>
<date>2019</date>
</item>
<item>
<title>[B][COLOR white]BOMBSHELL: THE HEDY LAMARR STORY[/COLOR] - [COLOR gold]7.4[/COLOR][/B]</title>
<link>movie=25494.mp4</link>
<info>Duração do filme: 1h, 28min</info>
<genre>Documentário</genre>
<date>2018</date>
</item>
<item>
<title>[B][COLOR white]BON COP BAD COP 2[/COLOR] - [COLOR gold]6.6[/COLOR][/B]</title>
<link>movie=12896.mp4</link>
<info>Duração do filme: 2h, 6min</info>
<genre>Crime, Comédia, Ação</genre>
<date>2017</date>
</item>
<item>
<title>[B][COLOR white]BONECA ASSASSINA[/COLOR][/B]</title>
<link>movie=28309.mp4</link>
<info>Duração do filme: 1h, 33min</info>
<genre>Terror</genre>
<date>1991</date>
</item>
<item>
<title>[B][COLOR white]BONECAS RUSSAS[/COLOR] - [COLOR gold]7.0[/COLOR][/B]</title>
<link>movie=29756.mp4</link>
<info>Duração do filme: 2h, 9min</info>
<genre>Comédia, Drama, Romance</genre>
<date>2005</date>
</item>
<item>
<title>[B][COLOR white]BONECO DE NEVE[/COLOR] - [COLOR gold]5.1[/COLOR][/B]</title>
<link>movie=24209.mp4</link>
<info>Duração do filme: 1h, 59min</info>
<genre>Crime, Suspense</genre>
<date>2017</date>
</item>
<item>
<title>[B][COLOR white]BONECO DO MAL[/COLOR] - [COLOR gold]6.0[/COLOR][/B]</title>
<link>movie=19039.mp4</link>
<info>Duração do filme: 1h, 37min</info>
<genre>Terror, Suspense, Mistério</genre>
<date>2016</date>
</item>
<item>
<title>[B][COLOR white]BONECOS DA MORTE[/COLOR] - [COLOR gold]5.7[/COLOR][/B]</title>
<link>movie=18590.mp4</link>
<info>Duração do filme: 1h, 30min</info>
<genre>Terror, Fantasia, Sci-Fi</genre>
<date>1989</date>
</item>
<item>
<title>[B][COLOR white]BONEQUINHA DE LUXO[/COLOR] - [COLOR gold]7.7[/COLOR][/B]</title>
<link>movie=21291.mp4</link>
<info>Duração do filme: 1h, 55min</info>
<genre>Comédia, Drama, Romance</genre>
<date>1961</date>
</item>
<item>
<title>[B][COLOR white]BONITINHA, MAS ORDINÁRIA[/COLOR] - [COLOR gold]5.1[/COLOR][/B]</title>
<link>movie=15755.mp4</link>
<info>Duração do filme: 1h, 30min</info>
<genre></genre>
<date>2013</date>
</item>
<item>
<title>[B][COLOR white]BONNIE E CLYDE - UMA RAJADA DE BALAS[/COLOR] - [COLOR gold]7.8[/COLOR][/B]</title>
<link>movie=18177.mp4</link>
<info>Duração do filme: 1h, 52min</info>
<genre>Crime, Drama</genre>
<date>1967</date>
</item>
<item>
<title>[B][COLOR white]BONS COSTUMES[/COLOR] - [COLOR gold]6.7[/COLOR][/B]</title>
<link>movie=18006.mp4</link>
<info>Duração do filme: 1h, 37min</info>
<genre>Comédia, Romance</genre>
<date>2008</date>
</item>
<item>
<title>[B][COLOR white]BONS DE BICO[/COLOR] - [COLOR gold]5.9[/COLOR][/B]</title>
<link>movie=20361.mp4</link>
<info>Duração do filme: 1h, 31min</info>
<genre>Animação, Comédia, Família</genre>
<date>2013</date>
</item>
<item>
<title>[B][COLOR white]BONS MENINOS[/COLOR] - [COLOR gold]6.7[/COLOR][/B]</title>
<link>movie=18514.mp4</link>
<info>Duração do filme: 1h, 29min</info>
<genre>Comédia</genre>
<date>2019</date>
</item>
<item>
<title>[B][COLOR white]BOO 2! O HALLOWEEN DE MADEA[/COLOR] - [COLOR gold]3.8[/COLOR][/B]</title>
<link>movie=22188.mp4</link>
<info>Duração do filme: 1h, 41min</info>
<genre>Terror, Comédia</genre>
<date>2017</date>
</item>
<item>
<title>[B][COLOR white]BOOGIE NIGHTS - PRAZER SEM LIMITES[/COLOR] - [COLOR gold]7.9[/COLOR][/B]</title>
<link>movie=19274.mp4</link>
<info>Duração do filme: 2h, 35min</info>
<genre>Drama</genre>
<date>1997</date>
</item>
<item>
<title>[B][COLOR white]BOOK OF BLOOD[/COLOR] - [COLOR gold]5.3[/COLOR][/B]</title>
<link>movie=14308.mp4</link>
<info>Duração do filme: 1h, 36min</info>
<genre>Terror, Drama, Mistério, Suspense</genre>
<date>2009</date>
</item>
<item>
<title>[B][COLOR white]BOOK OF MONSTERS[/COLOR] - [COLOR gold]4.7[/COLOR][/B]</title>
<link>movie=24928.mp4</link>
<info>Duração do filme: 1h, 24min</info>
<genre>Comédia, Terror, Ação</genre>
<date>2019</date>
</item>
<item>
<title>[B][COLOR white]BOONE: O CAÇADOR DE RECOMPENSAS[/COLOR] - [COLOR gold]5.5[/COLOR][/B]</title>
<link>movie=16665.mp4</link>
<info>Duração do filme: 1h, 26min</info>
<genre>Ação</genre>
<date>2017</date>
</item>
<item>
<title>[B][COLOR white]BORAT - O SEGUNDO MELHOR REPÓRTER DO GLORIOSO PAÍS CAZAQUISTÃO VIAJA À AMÉRICA[/COLOR] - [COLOR gold]7.3[/COLOR][/B]</title>
<link>movie=14615.mp4</link>
<info>Duração do filme: 1h, 22min</info>
<genre>Comédia</genre>
<date>2006</date>
</item>
<item>
<title>[B][COLOR white]BORAT: FITA DE CINEMA SEGUINTE[/COLOR] - [COLOR gold]7.4[/COLOR][/B]</title>
<link>movie=27446.mp4</link>
<info>Duração do filme: 1h, 35min</info>
<genre>Comédia</genre>
<date>2020</date>
</item>
<item>
<title>[B][COLOR white]BORBOLETA NEGRA[/COLOR] - [COLOR gold]6.2[/COLOR][/B]</title>
<link>movie=23855.mp4</link>
<info>Duração do filme: 1h, 33min</info>
<genre>Suspense</genre>
<date>2017</date>
</item>
<item>
<title>[B][COLOR white]BORDERLAND[/COLOR] - [COLOR gold]5.7[/COLOR][/B]</title>
<link>movie=26202.mp4</link>
<info>Duração do filme: 1h, 45min</info>
<genre>Crime, Terror, Suspense</genre>
<date>2007</date>
</item>
<item>
<title>[B][COLOR white]BORG VS MCENROE[/COLOR] - [COLOR gold]6.9[/COLOR][/B]</title>
<link>movie=15836.mp4</link>
<info>Duração do filme: 1h, 48min</info>
<genre>Drama, História</genre>
<date>2017</date>
</item>
<item>
<title>[B][COLOR white]BORGMAN[/COLOR] - [COLOR gold]6.7[/COLOR][/B]</title>
<link>movie=22647.mp4</link>
<info>Duração do filme: 1h, 53min</info>
<genre>Suspense, Drama</genre>
<date>2013</date>
</item>
<item>
<title>[B][COLOR white]BORN RACER[/COLOR] - [COLOR gold]5.7[/COLOR][/B]</title>
<link>movie=15026.mp4</link>
<info>Duração do filme: 1h, 28min</info>
<genre>Ação, Drama</genre>
<date>2018</date>
</item>
<item>
<title>[B][COLOR white]BORNLESS ONES[/COLOR] - [COLOR gold]4.6[/COLOR][/B]</title>
<link>movie=15401.mp4</link>
<info>Duração do filme: 1h, 21min</info>
<genre>Terror</genre>
<date>2016</date>
</item>
<item>
<title>[B][COLOR white]BORSTAL[/COLOR] - [COLOR gold]4.4[/COLOR][/B]</title>
<link>movie=16872.mp4</link>
<info>Duração do filme: 1h, 27min</info>
<genre>Drama</genre>
<date>2017</date>
</item>
<item>
<title>[B][COLOR white]BORUTO: NARUTO THE MOVIE[/COLOR] - [COLOR gold]7.9[/COLOR][/B]</title>
<link>movie=24438.mp4</link>
<info>Duração do filme: 1h, 40min</info>
<genre>Ação, Comédia, Animação</genre>
<date>2015</date>
</item>
<item>
<title>[B][COLOR white]BOSQUE MACABRO[/COLOR][/B]</title>
<link>movie=28620.mp4</link>
<info>Duração do filme: 1h, 39min</info>
<genre>Terror, Suspense</genre>
<date>2014</date>
</item>
<item>
<title>[B][COLOR white]BOTTOM OF THE WORLD[/COLOR] - [COLOR gold]5.3[/COLOR][/B]</title>
<link>movie=21445.mp4</link>
<info>Duração do filme: 1h, 25min</info>
<genre>Drama, Mistério, Suspense</genre>
<date>2017</date>
</item>
<item>
<title>[B][COLOR white]BOULEVARD[/COLOR] - [COLOR gold]5.8[/COLOR][/B]</title>
<link>movie=24539.mp4</link>
<info>Duração do filme: 1h, 28min</info>
<genre>Drama</genre>
<date>2014</date>
</item>
<item>
<title>[B][COLOR white]BOUND & BABYSITTING[/COLOR] - [COLOR gold]6.4[/COLOR][/B]</title>
<link>movie=13404.mp4</link>
<info>Duração do filme: 1h, 25min</info>
<genre>Família, tv movie, Comédia</genre>
<date>2015</date>
</item>
<item>
<title>[B][COLOR white]BOUND TO VENGEANCE[/COLOR] - [COLOR gold]5.6[/COLOR][/B]</title>
<link>movie=16612.mp4</link>
<info>Duração do filme: 1h, 20min</info>
<genre>Suspense, Terror</genre>
<date>2015</date>
</item>
<item>
<title>[B][COLOR white]BOY ERASED: UMA VERDADE ANULADA[/COLOR] - [COLOR gold]6.9[/COLOR][/B]</title>
<link>movie=18626.mp4</link>
<info>Duração do filme: 1h, 54min</info>
<genre>Drama, Lgbt</genre>
<date>2018</date>
</item>
<item>
<title>[B][COLOR white]BOY[/COLOR] - [COLOR gold]7.5[/COLOR][/B]</title>
<link>movie=23014.mp4</link>
<info>Duração do filme: 1h, 27min</info>
<genre>Drama, Comédia</genre>
<date>2010</date>
</item>
<item>
<title>[B][COLOR white]BOYHOOD - DA INFÂNCIA À JUVENTUDE[/COLOR] - [COLOR gold]7.9[/COLOR][/B]</title>
<link>movie=23842.mp4</link>
<info>Duração do filme: 2h, 45min</info>
<genre>Drama</genre>
<date>2014</date>
</item>
<item>
<title>[B][COLOR white]BOYKA: O IMBATÍVEL[/COLOR] - [COLOR gold]7.0[/COLOR][/B]</title>
<link>movie=23481.mp4</link>
<info>Duração do filme: 1h, 26min</info>
<genre>Suspense, Ação, Crime</genre>
<date>2016</date>
</item>
<item>
<title>[B][COLOR white]BOYS STATE[/COLOR] - [COLOR gold]7.7[/COLOR][/B]</title>
<link>movie=27278.mp4</link>
<info>Duração do filme: 1h, 49min</info>
<genre>Documentário</genre>
<date>2020</date>
</item>
<item>
<title>[B][COLOR white]BRACKENMORE[/COLOR] - [COLOR gold]4.2[/COLOR][/B]</title>
<link>movie=16929.mp4</link>
<info>Duração do filme: 1h, 12min</info>
<genre>Terror, Mistério, Suspense</genre>
<date>2017</date>
</item>
<item>
<title>[B][COLOR white]BRADDOCK - O SUPER COMANDO[/COLOR] - [COLOR gold]5.5[/COLOR][/B]</title>
<link>movie=18203.mp4</link>
<info>Duração do filme: 1h, 41min</info>
<genre>Ação, Aventura, Suspense, Guerra</genre>
<date>1984</date>
</item>
<item>
<title>[B][COLOR white]BRADDOCK 2 - O INÍCIO DA MISSÃO[/COLOR] - [COLOR gold]5.4[/COLOR][/B]</title>
<link>movie=13073.mp4</link>
<info>Duração do filme: 1h, 40min</info>
<genre>Ação, Guerra</genre>
<date>1985</date>
</item>
<item>
<title>[B][COLOR white]BRADDOCK 3 - O RESGATE[/COLOR] - [COLOR gold]4.9[/COLOR][/B]</title>
<link>movie=20836.mp4</link>
<info>Duração do filme: 1h, 41min</info>
<genre>Ação, Guerra</genre>
<date>1988</date>
</item>
<item>
<title>[B][COLOR white]BRAHMAN NAMAN[/COLOR] - [COLOR gold]5.6[/COLOR][/B]</title>
<link>movie=21481.mp4</link>
<info>Duração do filme: 1h, 34min</info>
<genre>Comédia</genre>
<date>2016</date>
</item>
<item>
<title>[B][COLOR white]BRAHMS: BONECO DO MAL II[/COLOR] - [COLOR gold]4.5[/COLOR][/B]</title>
<link>movie=26700.mp4</link>
<info>Duração do filme: 1h, 26min</info>
<genre>Terror, Mistério, Suspense</genre>
<date>2020</date>
</item>
<item>
<title>[B][COLOR white]BRANCA DE NEVE E O CAÇADOR[/COLOR] - [COLOR gold]6.1[/COLOR][/B]</title>
<link>movie=16011.mp4</link>
<info>Duração do filme: 2h, 7min</info>
<genre>Aventura, Fantasia, Drama</genre>
<date>2012</date>
</item>
<item>
<title>[B][COLOR white]BRANCA DE NEVE E OS SETE ANÕES[/COLOR] - [COLOR gold]7.6[/COLOR][/B]</title>
<link>movie=19014.mp4</link>
<info>Duração do filme: 1h, 23min</info>
<genre>Fantasia, Animação, Família</genre>
<date>1937</date>
</item>
<item>
<title>[B][COLOR white]BRANCA DE NEVE[/COLOR] - [COLOR gold]5.7[/COLOR][/B]</title>
<link>movie=29057.mp4</link>
<info>Duração do filme: 1h, 33min</info>
<genre>Aventura, Família, Fantasia, tv movie</genre>
<date>2001</date>
</item>
<item>
<title>[B][COLOR white]BRANCO SAI, PRETO FICA[/COLOR] - [COLOR gold]6.4[/COLOR][/B]</title>
<link>movie=28874.mp4</link>
<info>Duração do filme: 1h, 33min</info>
<genre>Sci-Fi, Documentário, Drama</genre>
<date>2014</date>
</item>
<item>
<title>[B][COLOR white]BRANQUINHA[/COLOR] - [COLOR gold]5.7[/COLOR][/B]</title>
<link>movie=20227.mp4</link>
<info>Duração do filme: 1h, 28min</info>
<genre>Drama</genre>
<date>2016</date>
</item>
<item>
<title>[B][COLOR white]BRASÍLIA, CONTRADIÇÕES DE UMA CIDADE NOVA[/COLOR] - [COLOR gold]7.4[/COLOR][/B]</title>
<link>movie=17381.mp4</link>
<info>Duração do filme: h, 22min</info>
<genre>Documentário</genre>
<date>1968</date>
</item>
<item>
<title>[B][COLOR white]BRATZ[/COLOR] - [COLOR gold]3.0[/COLOR][/B]</title>
<link>movie=18566.mp4</link>
<info>Duração do filme: 1h, 50min</info>
<genre>Comédia</genre>
<date>2007</date>
</item>
<item>
<title>[B][COLOR white]BRAVESTORM[/COLOR] - [COLOR gold]4.9[/COLOR][/B]</title>
<link>movie=28907.mp4</link>
<info>Duração do filme: 1h, 24min</info>
<genre>Ação, Aventura, Sci-Fi</genre>
<date>2017</date>
</item>
<item>
<title>[B][COLOR white]BRAVETOWN[/COLOR] - [COLOR gold]6.2[/COLOR][/B]</title>
<link>movie=22157.mp4</link>
<info>Duração do filme: 1h, 52min</info>
<genre>Drama, Músical</genre>
<date>2015</date>
</item>
<item>
<title>[B][COLOR white]BRAVURA INDÔMITA[/COLOR] - [COLOR gold]7.6[/COLOR][/B]</title>
<link>movie=19440.mp4</link>
<info>Duração do filme: 1h, 50min</info>
<genre>Drama, Aventura, Faroeste</genre>
<date>2010</date>
</item>
<item>
<title>[B][COLOR white]BRAVURA INDÔMITA[/COLOR][/B]</title>
<link>movie=28397.mp4</link>
<info>Duração do filme: 2h, 8min</info>
<genre>Faroeste, Drama, Aventura</genre>
<date>1969</date>
</item>
<item>
<title>[B][COLOR white]BRAZIL: O FILME[/COLOR] - [COLOR gold]7.9[/COLOR][/B]</title>
<link>movie=25526.mp4</link>
<info>Duração do filme: 2h, 12min</info>
<genre>Comédia, Sci-Fi</genre>
<date>1985</date>
</item>
<item>
<title>[B][COLOR white]BREAK BLADE 1: KAKUSEI NO TOKI[/COLOR] - [COLOR gold]7.1[/COLOR][/B]</title>
<link>movie=19366.mp4</link>
<info>Duração do filme: h, 51min</info>
<genre>Ação, Animação, Fantasia</genre>
<date>2010</date>
</item>
<item>
<title>[B][COLOR white]BREAK[/COLOR] - [COLOR gold]5.9[/COLOR][/B]</title>
<link>movie=27594.mp4</link>
<info>Duração do filme: 1h, 20min</info>
<genre>Comédia, Drama</genre>
<date>2018</date>
</item>
<item>
<title>[B][COLOR white]BREAKDOWN: IMPLACÁVEL PERSEGUIÇÃO[/COLOR][/B]</title>
<link>movie=29469.mp4</link>
<info>Duração do filme: 1h, 35min</info>
<genre>Suspense, Drama, Ação</genre>
<date>1997</date>
</item>
<item>
<title>[B][COLOR white]BREAKING FAST[/COLOR] - [COLOR gold]5.7[/COLOR][/B]</title>
<link>movie=27770.mp4</link>
<info>Duração do filme: 1h, 30min</info>
<genre>Comédia, Drama, Romance</genre>
<date>2020</date>
</item>
<item>
<title>[B][COLOR white]BREAKING LEGS[/COLOR] - [COLOR gold]4.2[/COLOR][/B]</title>
<link>movie=22516.mp4</link>
<info>Duração do filme: 1h, 37min</info>
<genre>Família</genre>
<date>2017</date>
</item>
<item>
<title>[B][COLOR white]BREAKING SURFACE[/COLOR] - [COLOR gold]6.1[/COLOR][/B]</title>
<link>movie=27633.mp4</link>
<info>Duração do filme: 1h, 22min</info>
<genre>Suspense, Drama, Ação</genre>
<date>2020</date>
</item>
<item>
<title>[B][COLOR white]BREAKING THE GIRLS[/COLOR] - [COLOR gold]5.1[/COLOR][/B]</title>
<link>movie=16150.mp4</link>
<info>Duração do filme: 1h, 23min</info>
<genre>Crime, Suspense</genre>
<date>2013</date>
</item>
<item>
<title>[B][COLOR white]BREAKING THROUGH: NO RITMO DO CORAÇÃO[/COLOR] - [COLOR gold]4.3[/COLOR][/B]</title>
<link>movie=23105.mp4</link>
<info>Duração do filme: 1h, 24min</info>
<genre>Músical, Drama</genre>
<date>2015</date>
</item>
<item>
<title>[B][COLOR white]BRESLIN AND HAMILL: DEADLINE ARTISTS[/COLOR] - [COLOR gold]8.0[/COLOR][/B]</title>
<link>movie=27247.mp4</link>
<info>Duração do filme: 1h, 46min</info>
<genre>Documentário</genre>
<date>2018</date>
</item>
<item>
<title>[B][COLOR white]BREVE MIRAGEM DE SOL[/COLOR] - [COLOR gold]6.1[/COLOR][/B]</title>
<link>movie=27771.mp4</link>
<info>Duração do filme: 1h, 35min</info>
<genre>Drama</genre>
<date>2020</date>
</item>
<item>
<title>[B][COLOR white]BREXIT - A GUERRA UNCIVIL[/COLOR] - [COLOR gold]7.0[/COLOR][/B]</title>
<link>movie=23041.mp4</link>
<info>Duração do filme: 1h, 33min</info>
<genre>História, tv movie, Drama</genre>
<date>2019</date>
</item>
<item>
<title>[B][COLOR white]BRIAN REGAN: NUNCHUCKS AND FLAMETHROWERS[/COLOR] - [COLOR gold]6.2[/COLOR][/B]</title>
<link>movie=14897.mp4</link>
<info>Duração do filme: 1h, 1min</info>
<genre>Comédia</genre>
<date>2017</date>
</item>
<item>
<title>[B][COLOR white]BRIAN REGAN: ON THE ROCKS[/COLOR] - [COLOR gold]7.0[/COLOR][/B]</title>
<link>movie=27764.mp4</link>
<info>Duração do filme: h, 58min</info>
<genre>Comédia</genre>
<date>2021</date>
</item>
<item>
<title>[B][COLOR white]BRIDGEND[/COLOR] - [COLOR gold]5.5[/COLOR][/B]</title>
<link>movie=25655.mp4</link>
<info>Duração do filme: 1h, 35min</info>
<genre>Drama</genre>
<date>2015</date>
</item>
<item>
<title>[B][COLOR white]BRIDGET JONES: NO LIMITE DA RAZÃO[/COLOR] - [COLOR gold]6.0[/COLOR][/B]</title>
<link>movie=20890.mp4</link>
<info>Duração do filme: 1h, 48min</info>
<genre>Comédia, Romance</genre>
<date>2004</date>
</item>
<item>
<title>[B][COLOR white]BRIGADA 49[/COLOR] - [COLOR gold]6.5[/COLOR][/B]</title>
<link>movie=15753.mp4</link>
<info>Duração do filme: 1h, 55min</info>
<genre>Drama, Ação, Suspense</genre>
<date>2004</date>
</item>
<item>
<title>[B][COLOR white]BRIGHT LIGHTS: STARRING CARRIE FISHER AND DEBBIE REYNOLDS[/COLOR] - [COLOR gold]8.0[/COLOR][/B]</title>
<link>movie=25333.mp4</link>
<info>Duração do filme: 1h, 35min</info>
<genre>Documentário</genre>
<date>2016</date>
</item>
<item>
<title>[B][COLOR white]BRIGHT[/COLOR] - [COLOR gold]6.3[/COLOR][/B]</title>
<link>movie=29468.mp4</link>
<info>Duração do filme: 1h, 57min</info>
<genre>Fantasia, Ação, Suspense</genre>
<date>2017</date>
</item>
<item>
<title>[B][COLOR white]BRIGHTBURN - FILHO DAS TREVAS[/COLOR] - [COLOR gold]6.1[/COLOR][/B]</title>
<link>movie=13460.mp4</link>
<info>Duração do filme: 1h, 31min</info>
<genre>Terror, Sci-Fi, Suspense</genre>
<date>2019</date>
</item>
<item>
<title>[B][COLOR white]BRILHO DE UMA PAIXÃO[/COLOR] - [COLOR gold]6.9[/COLOR][/B]</title>
<link>movie=20654.mp4</link>
<info>Duração do filme: 1h, 59min</info>
<genre>Drama, Romance</genre>
<date>2009</date>
</item>
<item>
<title>[B][COLOR white]BRILHO ETERNO DE UMA MENTE SEM LEMBRANÇAS[/COLOR] - [COLOR gold]8.3[/COLOR][/B]</title>
<link>movie=24239.mp4</link>
<info>Duração do filme: 1h, 48min</info>
<genre>Sci-Fi, Drama, Romance</genre>
<date>2004</date>
</item>
<item>
<title>[B][COLOR white]BRILHO ETERNO[/COLOR] - [COLOR gold]5.6[/COLOR][/B]</title>
<link>movie=24941.mp4</link>
<info>Duração do filme: 1h, 25min</info>
<genre>Suspense</genre>
<date>2016</date>
</item>
<item>
<title>[B][COLOR white]BRINCADEIRA DE CRIANÇA[/COLOR][/B]</title>
<link>movie=28645.mp4</link>
<info>Duração do filme: 1h, 40min</info>
<genre>Suspense, Terror, Drama</genre>
<date>1972</date>
</item>
<item>
<title>[B][COLOR white]BRINCADEIRA MORTAL[/COLOR][/B]</title>
<link>movie=29274.mp4</link>
<info>Duração do filme: 1h, 31min</info>
<genre>Terror, Suspense, Drama, Mistério</genre>
<date>2019</date>
</item>
<item>
<title>[B][COLOR white]BRINCANDO COM FOGO[/COLOR] - [COLOR gold]4.9[/COLOR][/B]</title>
<link>movie=25760.mp4</link>
<info>Duração do filme: 1h, 36min</info>
<genre>Comédia, Família</genre>
<date>2019</date>
</item>
<item>
<title>[B][COLOR white]BRINCANDO COM TUBARÕES[/COLOR] - [COLOR gold]8.3[/COLOR][/B]</title>
<link>movie=29859.mp4</link>
<info>Duração do filme: 1h, 30min</info>
<genre>Documentário</genre>
<date>2021</date>
</item>
<item>
<title>[B][COLOR white]BRINCANDO DE SEDUZIR[/COLOR] - [COLOR gold]7.1[/COLOR][/B]</title>
<link>movie=14117.mp4</link>
<info>Duração do filme: 1h, 52min</info>
<genre>Comédia, Drama, Romance</genre>
<date>1996</date>
</item>
<item>
<title>[B][COLOR white]BRINQUEDO ASSASSINO 2[/COLOR] - [COLOR gold]5.8[/COLOR][/B]</title>
<link>movie=17190.mp4</link>
<info>Duração do filme: 1h, 24min</info>
<genre>Drama, Terror</genre>
<date>1990</date>
</item>
<item>
<title>[B][COLOR white]BRINQUEDO ASSASSINO 3[/COLOR] - [COLOR gold]5.1[/COLOR][/B]</title>
<link>movie=18971.mp4</link>
<info>Duração do filme: 1h, 30min</info>
<genre>Suspense, Terror, Ação</genre>
<date>1991</date>
</item>
<item>
<title>[B][COLOR white]BRINQUEDO ASSASSINO[/COLOR] - [COLOR gold]5.8[/COLOR][/B]</title>
<link>movie=24969.mp4</link>
<info>Duração do filme: 2h, 0min</info>
<genre>Terror</genre>
<date>2019</date>
</item>
<item>
<title>[B][COLOR white]BRINQUEDO ASSASSINO[/COLOR] - [COLOR gold]6.6[/COLOR][/B]</title>
<link>movie=18640.mp4</link>
<info>Duração do filme: 1h, 27min</info>
<genre>Terror</genre>
<date>1988</date>
</item>
<item>
<title>[B][COLOR white]BRINQUEDOS DIABÓLICOS[/COLOR] - [COLOR gold]5.1[/COLOR][/B]</title>
<link>movie=28234.mp4</link>
<info>Duração do filme: 1h, 26min</info>
<genre>Terror</genre>
<date>1992</date>
</item>
<item>
<title>[B][COLOR white]BRITNEY EVER AFTER[/COLOR] - [COLOR gold]2.5[/COLOR][/B]</title>
<link>movie=18418.mp4</link>
<info>Duração do filme: 2h, 0min</info>
<genre>Drama, tv movie</genre>
<date>2017</date>
</item>
<item>
<title>[B][COLOR white]BRITNEY: FOR THE RECORD[/COLOR] - [COLOR gold]7.7[/COLOR][/B]</title>
<link>movie=22849.mp4</link>
<info>Duração do filme: 1h, 0min</info>
<genre>Músical, Documentário</genre>
<date>2008</date>
</item>
<item>
<title>[B][COLOR white]BRO, WHAT HAPPENED?[/COLOR] - [COLOR gold]3.2[/COLOR][/B]</title>
<link>movie=16114.mp4</link>
<info>Duração do filme: 1h, 26min</info>
<genre>Comédia</genre>
<date>2014</date>
</item>
<item>
<title>[B][COLOR white]BROADWAY DANNY ROSE[/COLOR] - [COLOR gold]7.4[/COLOR][/B]</title>
<link>movie=19327.mp4</link>
<info>Duração do filme: 1h, 24min</info>
<genre>Comédia</genre>
<date>1984</date>
</item>
<item>
<title>[B][COLOR white]BRÓDER[/COLOR] - [COLOR gold]6.6[/COLOR][/B]</title>
<link>movie=25835.mp4</link>
<info>Duração do filme: 1h, 33min</info>
<genre>Drama</genre>
<date>2010</date>
</item>