<item>
<title>[B][COLOR gold]l[/COLOR] [COLOR white]PRÓXIMA PÁGINA: [COLOR gold]53[/COLOR][/COLOR][/B]</title>
<link>here</link>
<thumbnail>https://i.imgur.com/osBDac3.jpg</thumbnail>
<externallink>https://raw.github.com/skyrisk/brazucaplay/master/outros/filmes/page53.xml</externallink>
<info>[B][COLOR white]TODOS OS MELHORES FILMES EM [COLOR gold]ORDEM ALFABÉTICA[/COLOR][/COLOR][/B]</info>
<fanart>https://i.imgur.com/225XKdt.jpg</fanart>
</item>
<item>
<title>[B][COLOR white]UMA AVENTURA NA AMÉRICA SELVAGEM[/COLOR] - [COLOR gold]6.4[/COLOR][/B]</title>
<link>movie=28656.mp4</link>
<info>Duração do filme: 1h, 46min</info>
<genre>Família, Aventura</genre>
<date>1997</date>
</item>
<item>
<title>[B][COLOR white]UMA AVENTURA NO GELO[/COLOR] - [COLOR gold]4.7[/COLOR][/B]</title>
<link>movie=28993.mp4</link>
<info>Duração do filme: 1h, 34min</info>
<genre>Animação, Família</genre>
<date>2015</date>
</item>
<item>
<title>[B][COLOR white]UMA AVENTURA PERIGOSA[/COLOR] - [COLOR gold]7.0[/COLOR][/B]</title>
<link>movie=29483.mp4</link>
<info>Duração do filme: 1h, 57min</info>
<genre>Drama, Crime, Documentário</genre>
<date>2018</date>
</item>
<item>
<title>[B][COLOR white]UMA BABÁ EM MINHA VIDA[/COLOR][/B]</title>
<link>movie=29482.mp4</link>
<info>Duração do filme: 1h, 26min</info>
<genre>Comédia, Drama, Romance, tv movie</genre>
<date>2016</date>
</item>
<item>
<title>[B][COLOR white]UMA BABÁ QUASE PERFEITA[/COLOR] - [COLOR gold]7.0[/COLOR][/B]</title>
<link>movie=24221.mp4</link>
<info>Duração do filme: 2h, 5min</info>
<genre>Comédia, Drama, Família</genre>
<date>1993</date>
</item>
<item>
<title>[B][COLOR white]UMA BATALHA DE FÉ[/COLOR][/B]</title>
<link>movie=29096.mp4</link>
<info>Duração do filme: 1h, 27min</info>
<genre>Drama</genre>
<date>2019</date>
</item>
<item>
<title>[B][COLOR white]UMA BELEZA FANTÁSTICA[/COLOR] - [COLOR gold]6.9[/COLOR][/B]</title>
<link>movie=16846.mp4</link>
<info>Duração do filme: 1h, 40min</info>
<genre>Comédia, Drama, Fantasia, Romance</genre>
<date>2016</date>
</item>
<item>
<title>[B][COLOR white]UMA BOA AÇÃO[/COLOR] - [COLOR gold]5.6[/COLOR][/B]</title>
<link>movie=29481.mp4</link>
<info>Duração do filme: 1h, 51min</info>
<genre>Comédia, Drama, Romance</genre>
<date>2012</date>
</item>
<item>
<title>[B][COLOR white]UMA BOA E VELHA ORGIA[/COLOR] - [COLOR gold]6.1[/COLOR][/B]</title>
<link>movie=22150.mp4</link>
<info>Duração do filme: 1h, 35min</info>
<genre>Comédia</genre>
<date>2011</date>
</item>
<item>
<title>[B][COLOR white]UMA BOA HISTÓRIA[/COLOR] - [COLOR gold]5.8[/COLOR][/B]</title>
<link>movie=28886.mp4</link>
<info>Duração do filme: 1h, 22min</info>
<genre>Drama</genre>
<date>2020</date>
</item>
<item>
<title>[B][COLOR white]UMA BREVE HISTÓRIA DO TEMPO[/COLOR] - [COLOR gold]7.3[/COLOR][/B]</title>
<link>movie=22338.mp4</link>
<info>Duração do filme: 1h, 18min</info>
<genre>Documentário</genre>
<date>1991</date>
</item>
<item>
<title>[B][COLOR white]UMA CAMINHADA NA FLORESTA[/COLOR] - [COLOR gold]6.3[/COLOR][/B]</title>
<link>movie=19926.mp4</link>
<info>Duração do filme: 1h, 44min</info>
<genre>Aventura, Comédia, Drama</genre>
<date>2015</date>
</item>
<item>
<title>[B][COLOR white]UMA CANÇÃO DE AMOR PARA BOBBY LONG[/COLOR] - [COLOR gold]7.1[/COLOR][/B]</title>
<link>movie=21610.mp4</link>
<info>Duração do filme: 1h, 59min</info>
<genre>Drama</genre>
<date>2004</date>
</item>
<item>
<title>[B][COLOR white]UMA CANÇÃO DE NATAL[/COLOR][/B]</title>
<link>movie=29480.mp4</link>
<info>Duração do filme: 1h, 30min</info>
<genre>Romance, tv movie</genre>
<date>2017</date>
</item>
<item>
<title>[B][COLOR white]UMA CANÇÃO PARA ELA[/COLOR] - [COLOR gold]6.0[/COLOR][/B]</title>
<link>movie=25023.mp4</link>
<info>Duração do filme: 1h, 56min</info>
<genre>Músical, Romance, Drama</genre>
<date>2014</date>
</item>
<item>
<title>[B][COLOR white]UMA CANÇÃO PARA LATASHA[/COLOR] - [COLOR gold]6.8[/COLOR][/B]</title>
<link>movie=28790.mp4</link>
<info>Duração do filme: h, 19min</info>
<genre>Documentário</genre>
<date>2019</date>
</item>
<item>
<title>[B][COLOR white]UMA CARTA DE AMOR[/COLOR] - [COLOR gold]6.3[/COLOR][/B]</title>
<link>movie=17384.mp4</link>
<info>Duração do filme: 2h, 11min</info>
<genre>Romance, Drama</genre>
<date>1999</date>
</item>
<item>
<title>[B][COLOR white]UMA CASA DE PERNAS PRO AR[/COLOR] - [COLOR gold]4.2[/COLOR][/B]</title>
<link>movie=19976.mp4</link>
<info>Duração do filme: 1h, 32min</info>
<genre>Comédia, Família</genre>
<date>2007</date>
</item>
<item>
<title>[B][COLOR white]UMA CHAMADA PERDIDA 2[/COLOR] - [COLOR gold]5.4[/COLOR][/B]</title>
<link>movie=22956.mp4</link>
<info>Duração do filme: 1h, 45min</info>
<genre>Mistério, Terror, Suspense</genre>
<date>2005</date>
</item>
<item>
<title>[B][COLOR white]UMA CHAMADA PERDIDA 3[/COLOR] - [COLOR gold]5.0[/COLOR][/B]</title>
<link>movie=13809.mp4</link>
<info>Duração do filme: 1h, 49min</info>
<genre>Terror</genre>
<date>2006</date>
</item>
<item>
<title>[B][COLOR white]UMA CHAMADA PERDIDA[/COLOR] - [COLOR gold]4.0[/COLOR][/B]</title>
<link>movie=12903.mp4</link>
<info>Duração do filme: 1h, 27min</info>
<genre>Terror, Mistério, Suspense</genre>
<date>2008</date>
</item>
<item>
<title>[B][COLOR white]UMA CHAMADA PERDIDA[/COLOR] - [COLOR gold]6.2[/COLOR][/B]</title>
<link>movie=22947.mp4</link>
<info>Duração do filme: 1h, 52min</info>
<genre>Terror, Suspense</genre>
<date>2003</date>
</item>
<item>
<title>[B][COLOR white]UMA CIDADE SEM LEI[/COLOR] - [COLOR gold]6.2[/COLOR][/B]</title>
<link>movie=24603.mp4</link>
<info>Duração do filme: 1h, 58min</info>
<genre>Suspense, Ação, Drama</genre>
<date>2010</date>
</item>
<item>
<title>[B][COLOR white]UMA CILADA PARA ROGER RABBIT[/COLOR] - [COLOR gold]7.7[/COLOR][/B]</title>
<link>movie=18206.mp4</link>
<info>Duração do filme: 1h, 43min</info>
<genre>Fantasia, Animação, Comédia, Crime, Família</genre>
<date>1988</date>
</item>
<item>
<title>[B][COLOR white]UMA COMÉDIA NADA ROMÂNTICA[/COLOR] - [COLOR gold]2.8[/COLOR][/B]</title>
<link>movie=27424.mp4</link>
<info>Duração do filme: 1h, 23min</info>
<genre>Comédia</genre>
<date>2006</date>
</item>
<item>
<title>[B][COLOR white]UMA CONEXÃO PARA O NATAL[/COLOR][/B]</title>
<link>movie=29479.mp4</link>
<info>Duração do filme: 1h, 24min</info>
<genre>Drama, tv movie, Mistério, Romance</genre>
<date>2017</date>
</item>
<item>
<title>[B][COLOR white]UMA CRIANÇA COMO JAKE[/COLOR] - [COLOR gold]5.4[/COLOR][/B]</title>
<link>movie=29478.mp4</link>
<info>Duração do filme: 1h, 32min</info>
<genre>Drama</genre>
<date>2018</date>
</item>
<item>
<title>[B][COLOR white]UMA CRIATURA GENTIL[/COLOR] - [COLOR gold]6.6[/COLOR][/B]</title>
<link>movie=14156.mp4</link>
<info>Duração do filme: 2h, 23min</info>
<genre>Drama, Mistério</genre>
<date>2017</date>
</item>
<item>
<title>[B][COLOR white]UMA DAMA DE ÓCULOS ESCUROS COM UMA ARMA NO CARRO[/COLOR] - [COLOR gold]5.5[/COLOR][/B]</title>
<link>movie=14900.mp4</link>
<info>Duração do filme: 1h, 33min</info>
<genre>Suspense</genre>
<date>2015</date>
</item>
<item>
<title>[B][COLOR white]UMA DOBRA NO TEMPO[/COLOR] - [COLOR gold]4.2[/COLOR][/B]</title>
<link>movie=20451.mp4</link>
<info>Duração do filme: 1h, 49min</info>
<genre>Aventura, Sci-Fi, Família, Fantasia</genre>
<date>2018</date>
</item>
<item>
<title>[B][COLOR white]UMA DOCE DISPUTA[/COLOR] - [COLOR gold]4.6[/COLOR][/B]</title>
<link>movie=24244.mp4</link>
<info>Duração do filme: 1h, 40min</info>
<genre>Romance, Comédia</genre>
<date>2016</date>
</item>
<item>
<title>[B][COLOR white]UMA DUPLA DESAJUSTADA[/COLOR] - [COLOR gold]7.1[/COLOR][/B]</title>
<link>movie=20810.mp4</link>
<info>Duração do filme: 1h, 51min</info>
<genre>Comédia</genre>
<date>1975</date>
</item>
<item>
<title>[B][COLOR white]UMA DUPLA GENIAL[/COLOR] - [COLOR gold]5.4[/COLOR][/B]</title>
<link>movie=21821.mp4</link>
<info>Duração do filme: 1h, 37min</info>
<genre>Comédia, Fantasia</genre>
<date>2013</date>
</item>
<item>
<title>[B][COLOR white]UMA DUPLA QUASE PERFEITA[/COLOR] - [COLOR gold]6.2[/COLOR][/B]</title>
<link>movie=22231.mp4</link>
<info>Duração do filme: 1h, 40min</info>
<genre>Ação, Comédia, Suspense, Crime, Família</genre>
<date>1989</date>
</item>
<item>
<title>[B][COLOR white]UMA EQUIPE MUITO ESPECIAL[/COLOR] - [COLOR gold]7.3[/COLOR][/B]</title>
<link>movie=18247.mp4</link>
<info>Duração do filme: 2h, 8min</info>
<genre>Comédia, Drama</genre>
<date>1992</date>
</item>
<item>
<title>[B][COLOR white]UMA ESCOLA ATRAPALHADA[/COLOR] - [COLOR gold]4.9[/COLOR][/B]</title>
<link>movie=28846.mp4</link>
<info>Duração do filme: 1h, 30min</info>
<genre>Comédia, Família</genre>
<date>1990</date>
</item>
<item>
<title>[B][COLOR white]UMA ESCOLA MUITO DOIDA[/COLOR] - [COLOR gold]5.6[/COLOR][/B]</title>
<link>movie=26492.mp4</link>
<info>Duração do filme: 1h, 26min</info>
<genre>Comédia</genre>
<date>1996</date>
</item>
<item>
<title>[B][COLOR white]UMA ESCOLA MUITO ESPECIAL, PARA GAROTAS[/COLOR] - [COLOR gold]5.3[/COLOR][/B]</title>
<link>movie=29165.mp4</link>
<info>Duração do filme: 1h, 29min</info>
<genre>Comédia, Romance</genre>
<date>1983</date>
</item>
<item>
<title>[B][COLOR white]UMA ESCOLA MUITO LOUCA[/COLOR] - [COLOR gold]5.3[/COLOR][/B]</title>
<link>movie=28236.mp4</link>
<info>Duração do filme: 1h, 44min</info>
<genre>Comédia</genre>
<date>1986</date>
</item>
<item>
<title>[B][COLOR white]UMA ESPERANÇA NO NATAL[/COLOR][/B]</title>
<link>movie=29094.mp4</link>
<info>Duração do filme: 1h, 41min</info>
<genre>Comédia, Drama</genre>
<date>2018</date>
</item>
<item>
<title>[B][COLOR white]UMA ESPOSA DE NATAL[/COLOR] - [COLOR gold]4.2[/COLOR][/B]</title>
<link>movie=30314.mp4</link>
<info>Duração do filme: 2h, 1min</info>
<genre>Comédia, Romance</genre>
<date>2021</date>
</item>
<item>
<title>[B][COLOR white]UMA ESTRADA PARA RECOMEÇAR[/COLOR] - [COLOR gold]6.2[/COLOR][/B]</title>
<link>movie=25772.mp4</link>
<info>Duração do filme: 1h, 18min</info>
<genre>Drama</genre>
<date>2019</date>
</item>
<item>
<title>[B][COLOR white]UMA ESTRELA NO PARAÍSO[/COLOR] - [COLOR gold]5.2[/COLOR][/B]</title>
<link>movie=20464.mp4</link>
<info>Duração do filme: 1h, 22min</info>
<genre>tv movie, Família</genre>
<date>2017</date>
</item>
<item>
<title>[B][COLOR white]UMA FAMÍLIA DE DOIS[/COLOR] - [COLOR gold]7.4[/COLOR][/B]</title>
<link>movie=16365.mp4</link>
<info>Duração do filme: 1h, 58min</info>
<genre>Drama, Comédia</genre>
<date>2016</date>
</item>
<item>
<title>[B][COLOR white]UMA FAMÍLIA EM APUROS[/COLOR] - [COLOR gold]6.0[/COLOR][/B]</title>
<link>movie=13341.mp4</link>
<info>Duração do filme: 1h, 44min</info>
<genre>Comédia</genre>
<date>2012</date>
</item>
<item>
<title>[B][COLOR white]UMA FAMÍLIA FELIZ[/COLOR] - [COLOR gold]4.8[/COLOR][/B]</title>
<link>movie=17052.mp4</link>
<info>Duração do filme: 1h, 33min</info>
<genre>Animação, Família, Fantasia, Comédia</genre>
<date>2017</date>
</item>
<item>
<title>[B][COLOR white]UMA FAZENDA DO BARULHO[/COLOR] - [COLOR gold]6.2[/COLOR][/B]</title>
<link>movie=14582.mp4</link>
<info>Duração do filme: 1h, 41min</info>
<genre>Comédia</genre>
<date>1988</date>
</item>
<item>
<title>[B][COLOR white]UMA FAZENDA MALUCA[/COLOR] - [COLOR gold]3.4[/COLOR][/B]</title>
<link>movie=28998.mp4</link>
<info>Duração do filme: 1h, 20min</info>
<genre>Animação, Comédia</genre>
<date>2008</date>
</item>
<item>
<title>[B][COLOR white]UMA FESTA NO AR[/COLOR] - [COLOR gold]4.5[/COLOR][/B]</title>
<link>movie=13467.mp4</link>
<info>Duração do filme: 1h, 26min</info>
<genre>Romance, Comédia</genre>
<date>2004</date>
</item>
<item>
<title>[B][COLOR white]UMA FLORESTA MUITO LOUCA[/COLOR] - [COLOR gold]5.3[/COLOR][/B]</title>
<link>movie=26493.mp4</link>
<info>Duração do filme: 1h, 37min</info>
<genre>Aventura, Comédia, Família, Animação</genre>
<date>2017</date>
</item>
<item>
<title>[B][COLOR white]UMA FORMA DE ASSASSINATO[/COLOR] - [COLOR gold]5.3[/COLOR][/B]</title>
<link>movie=21024.mp4</link>
<info>Duração do filme: 1h, 35min</info>
<genre>Drama, Suspense</genre>
<date>2016</date>
</item>
<item>
<title>[B][COLOR white]UMA GAROTA ENCANTADA[/COLOR] - [COLOR gold]6.3[/COLOR][/B]</title>
<link>movie=13620.mp4</link>
<info>Duração do filme: 1h, 36min</info>
<genre>Família, Fantasia, Comédia</genre>
<date>2004</date>
</item>
<item>
<title>[B][COLOR white]UMA GAROTA IRRESISTÍVEL[/COLOR] - [COLOR gold]6.5[/COLOR][/B]</title>
<link>movie=25200.mp4</link>
<info>Duração do filme: 1h, 30min</info>
<genre>Drama</genre>
<date>2006</date>
</item>
<item>
<title>[B][COLOR white]UMA GUERRA PESSOAL[/COLOR] - [COLOR gold]6.7[/COLOR][/B]</title>
<link>movie=13815.mp4</link>
<info>Duração do filme: 1h, 46min</info>
<genre>Drama, Guerra</genre>
<date>2018</date>
</item>
<item>
<title>[B][COLOR white]UMA HISTÓRIA DE AMOR E FÚRIA[/COLOR] - [COLOR gold]7.2[/COLOR][/B]</title>
<link>movie=22192.mp4</link>
<info>Duração do filme: 1h, 15min</info>
<genre>Animação, Drama, História, Romance, Sci-Fi</genre>
<date>2013</date>
</item>
<item>
<title>[B][COLOR white]UMA HISTÓRIA DE NATAL[/COLOR] - [COLOR gold]8.0[/COLOR][/B]</title>
<link>movie=25190.mp4</link>
<info>Duração do filme: 1h, 34min</info>
<genre>Comédia, Família</genre>
<date>1983</date>
</item>
<item>
<title>[B][COLOR white]UMA HISTÓRIA DE VINGANÇA[/COLOR] - [COLOR gold]5.2[/COLOR][/B]</title>
<link>movie=20515.mp4</link>
<info>Duração do filme: 1h, 39min</info>
<genre>Suspense, Drama</genre>
<date>2017</date>
</item>
<item>
<title>[B][COLOR white]UMA HISTÓRIA REAL[/COLOR] - [COLOR gold]8.0[/COLOR][/B]</title>
<link>movie=21226.mp4</link>
<info>Duração do filme: 1h, 52min</info>
<genre>Drama</genre>
<date>1999</date>
</item>
<item>
<title>[B][COLOR white]UMA INVENÇÃO DE NATAL[/COLOR] - [COLOR gold]6.6[/COLOR][/B]</title>
<link>movie=27497.mp4</link>
<info>Duração do filme: 1h, 59min</info>
<genre>Família, Fantasia, Músical</genre>
<date>2020</date>
</item>
<item>
<title>[B][COLOR white]UMA IRMÃ NADA PERFEITA[/COLOR] - [COLOR gold]4.8[/COLOR][/B]</title>
<link>movie=14772.mp4</link>
<info>Duração do filme: 1h, 50min</info>
<genre>Comédia, Drama, Romance</genre>
<date>2018</date>
</item>
<item>
<title>[B][COLOR white]UMA JANELA PARA O AMOR[/COLOR] - [COLOR gold]7.3[/COLOR][/B]</title>
<link>movie=20340.mp4</link>
<info>Duração do filme: 1h, 57min</info>
<genre>Drama, Romance</genre>
<date>1985</date>
</item>
<item>
<title>[B][COLOR white]UMA JORNADA DE PERDÃO[/COLOR] - [COLOR gold]5.8[/COLOR][/B]</title>
<link>movie=26729.mp4</link>
<info>Duração do filme: 1h, 30min</info>
<genre>Drama</genre>
<date>2018</date>
</item>
<item>
<title>[B][COLOR white]UMA JORNADA PARA TODA A VIDA[/COLOR] - [COLOR gold]7.2[/COLOR][/B]</title>
<link>movie=17506.mp4</link>
<info>Duração do filme: 1h, 52min</info>
<genre>Aventura, Drama</genre>
<date>2013</date>
</item>
<item>
<title>[B][COLOR white]UMA LADRA SEM LIMITES[/COLOR] - [COLOR gold]5.7[/COLOR][/B]</title>
<link>movie=14774.mp4</link>
<info>Duração do filme: 1h, 51min</info>
<genre>Comédia, Crime</genre>
<date>2013</date>
</item>
<item>
<title>[B][COLOR white]UMA LIÇÃO DE AMOR[/COLOR] - [COLOR gold]7.7[/COLOR][/B]</title>
<link>movie=15503.mp4</link>
<info>Duração do filme: 2h, 12min</info>
<genre>Drama</genre>
<date>2001</date>
</item>
<item>
<title>[B][COLOR white]UMA LIÇÃO DE VIDA[/COLOR] - [COLOR gold]7.4[/COLOR][/B]</title>
<link>movie=26488.mp4</link>
<info>Duração do filme: 1h, 43min</info>
<genre>Romance, Drama</genre>
<date>2010</date>
</item>
<item>
<title>[B][COLOR white]UMA LINDA MULHER[/COLOR] - [COLOR gold]7.0[/COLOR][/B]</title>
<link>movie=24258.mp4</link>
<info>Duração do filme: 1h, 59min</info>
<genre>Romance, Comédia</genre>
<date>1990</date>
</item>
<item>
<title>[B][COLOR white]UMA LONGA JORNADA[/COLOR] - [COLOR gold]7.1[/COLOR][/B]</title>
<link>movie=15047.mp4</link>
<info>Duração do filme: 2h, 8min</info>
<genre>Drama, Romance</genre>
<date>2015</date>
</item>
<item>
<title>[B][COLOR white]UMA LONGA QUEDA[/COLOR] - [COLOR gold]6.4[/COLOR][/B]</title>
<link>movie=14126.mp4</link>
<info>Duração do filme: 1h, 36min</info>
<genre>Comédia, Drama</genre>
<date>2014</date>
</item>
<item>
<title>[B][COLOR white]UMA LONGA VIAGEM[/COLOR] - [COLOR gold]7.1[/COLOR][/B]</title>
<link>movie=20078.mp4</link>
<info>Duração do filme: 1h, 56min</info>
<genre>Drama, História</genre>
<date>2013</date>
</item>
<item>
<title>[B][COLOR white]UMA LOUCURA DE MULHER[/COLOR] - [COLOR gold]5.2[/COLOR][/B]</title>
<link>movie=26487.mp4</link>
<info>Duração do filme: 1h, 32min</info>
<genre>Romance, Comédia</genre>
<date>2016</date>
</item>
<item>
<title>[B][COLOR white]UMA LUZ NA ESCURIDÃO[/COLOR] - [COLOR gold]6.5[/COLOR][/B]</title>
<link>movie=15086.mp4</link>
<info>Duração do filme: 2h, 12min</info>
<genre>Drama, Romance</genre>
<date>1992</date>
</item>
<item>
<title>[B][COLOR white]UMA MÃE EM APUROS[/COLOR] - [COLOR gold]4.6[/COLOR][/B]</title>
<link>movie=14658.mp4</link>
<info>Duração do filme: 1h, 30min</info>
<genre>Comédia, Drama</genre>
<date>2009</date>
</item>
<item>
<title>[B][COLOR white]UMA MÃE PARA O MEU BEBÊ[/COLOR] - [COLOR gold]6.0[/COLOR][/B]</title>
<link>movie=14882.mp4</link>
<info>Duração do filme: 1h, 39min</info>
<genre>Comédia</genre>
<date>2008</date>
</item>
<item>
<title>[B][COLOR white]UMA MANHÃ GLORIOSA[/COLOR] - [COLOR gold]6.5[/COLOR][/B]</title>
<link>movie=20248.mp4</link>
<info>Duração do filme: 1h, 42min</info>
<genre>Comédia, Drama, Romance</genre>
<date>2010</date>
</item>
<item>
<title>[B][COLOR white]UMA MENSAGEM ATRAVÉS DO TEMPO[/COLOR][/B]</title>
<link>movie=29233.mp4</link>
<info>Duração do filme: 1h, 0min</info>
<genre>Drama, Família</genre>
<date>2019</date>
</item>
<item>
<title>[B][COLOR white]UMA MENTE BRILHANTE[/COLOR] - [COLOR gold]8.2[/COLOR][/B]</title>
<link>movie=22943.mp4</link>
<info>Duração do filme: 2h, 15min</info>
<genre>Drama, Romance</genre>
<date>2001</date>
</item>
<item>
<title>[B][COLOR white]UMA MORTE NO GUNJ[/COLOR] - [COLOR gold]7.5[/COLOR][/B]</title>
<link>movie=16349.mp4</link>
<info>Duração do filme: 1h, 50min</info>
<genre>Drama, Suspense</genre>
<date>2016</date>
</item>
<item>
<title>[B][COLOR white]UMA MULHER ALTA[/COLOR] - [COLOR gold]7.1[/COLOR][/B]</title>
<link>movie=27171.mp4</link>
<info>Duração do filme: 2h, 10min</info>
<genre>Drama</genre>
<date>2019</date>
</item>
<item>
<title>[B][COLOR white]UMA MULHER EM GUERRA[/COLOR] - [COLOR gold]7.4[/COLOR][/B]</title>
<link>movie=20277.mp4</link>
<info>Duração do filme: 1h, 41min</info>
<genre>Suspense, Drama, Comédia</genre>
<date>2018</date>
</item>
<item>
<title>[B][COLOR white]UMA MULHER EXTRAORDINÁRIA[/COLOR] - [COLOR gold]7.7[/COLOR][/B]</title>
<link>movie=27740.mp4</link>
<info>Duração do filme: 1h, 30min</info>
<genre>Drama, Crime</genre>
<date>2019</date>
</item>
<item>
<title>[B][COLOR white]UMA MULHER FANTÁSTICA[/COLOR] - [COLOR gold]7.2[/COLOR][/B]</title>
<link>movie=24599.mp4</link>
<info>Duração do filme: 1h, 44min</info>
<genre>Drama, Lgbt</genre>
<date>2017</date>
</item>
<item>
<title>[B][COLOR white]UMA MULHER PARA DOIS[/COLOR] - [COLOR gold]6.2[/COLOR][/B]</title>
<link>movie=17516.mp4</link>
<info>Duração do filme: 1h, 36min</info>
<genre>Comédia, Crime, Romance, Drama</genre>
<date>1993</date>
</item>
<item>
<title>[B][COLOR white]UMA MULHER SOB INFLUÊNCIA[/COLOR] - [COLOR gold]8.2[/COLOR][/B]</title>
<link>movie=20857.mp4</link>
<info>Duração do filme: 2h, 35min</info>
<genre>Drama</genre>
<date>1974</date>
</item>
<item>
<title>[B][COLOR white]UMA NOITE ALUCINANTE 2[/COLOR] - [COLOR gold]7.8[/COLOR][/B]</title>
<link>movie=23417.mp4</link>
<info>Duração do filme: 1h, 24min</info>
<genre>Terror, Comédia, Fantasia</genre>
<date>1987</date>
</item>
<item>
<title>[B][COLOR white]UMA NOITE ALUCINANTE 3[/COLOR] - [COLOR gold]7.5[/COLOR][/B]</title>
<link>movie=15956.mp4</link>
<info>Duração do filme: 1h, 36min</info>
<genre>Fantasia, Terror, Comédia</genre>
<date>1992</date>
</item>
<item>
<title>[B][COLOR white]UMA NOITE ALUCINANTE: A MORTE DO DEMÔNIO[/COLOR] - [COLOR gold]7.5[/COLOR][/B]</title>
<link>movie=16954.mp4</link>
<info>Duração do filme: 1h, 25min</info>
<genre>Terror</genre>
<date>1981</date>
</item>
<item>
<title>[B][COLOR white]UMA NOITE COM A FAMÍLIA BLACKS[/COLOR] - [COLOR gold]4.8[/COLOR][/B]</title>
<link>movie=17828.mp4</link>
<info>Duração do filme: 1h, 30min</info>
<genre>Comédia, Terror</genre>
<date>2016</date>
</item>
<item>
<title>[B][COLOR white]UMA NOITE COM BEVERLY LUFF LINN[/COLOR] - [COLOR gold]5.7[/COLOR][/B]</title>
<link>movie=17302.mp4</link>
<info>Duração do filme: 1h, 48min</info>
<genre>Comédia, Crime</genre>
<date>2018</date>
</item>
<item>
<title>[B][COLOR white]UMA NOITE COM EDGAR ALLAN POE[/COLOR] - [COLOR gold]7.5[/COLOR][/B]</title>
<link>movie=19691.mp4</link>
<info>Duração do filme: h, 53min</info>
<genre>Drama, Terror, Mistério</genre>
<date>1970</date>
</item>
<item>
<title>[B][COLOR white]UMA NOITE DE 12 ANOS[/COLOR] - [COLOR gold]7.6[/COLOR][/B]</title>
<link>movie=17576.mp4</link>
<info>Duração do filme: 2h, 2min</info>
<genre>Drama, Crime, História</genre>
<date>2018</date>
</item>
<item>
<title>[B][COLOR white]UMA NOITE DE AMOR E MÚSICA[/COLOR] - [COLOR gold]6.6[/COLOR][/B]</title>
<link>movie=17518.mp4</link>
<info>Duração do filme: 1h, 30min</info>
<genre>Comédia, Músical, Romance</genre>
<date>2008</date>
</item>
<item>
<title>[B][COLOR white]UMA NOITE DE CRIME 5:  A FRONTEIRA[/COLOR] - [COLOR gold]5.5[/COLOR][/B]</title>
<link>movie=29845.mp4</link>
<info>Duração do filme: 1h, 43min</info>
<genre>Aventura, Suspense, Ação, Terror, Faroeste</genre>
<date>2021</date>
</item>
<item>
<title>[B][COLOR white]UMA NOITE DE CRIME: ANARQUIA[/COLOR] - [COLOR gold]6.4[/COLOR][/B]</title>
<link>movie=15516.mp4</link>
<info>Duração do filme: 1h, 44min</info>
<genre>Terror, Suspense</genre>
<date>2014</date>
</item>
<item>
<title>[B][COLOR white]UMA NOITE DE CRIME[/COLOR] - [COLOR gold]5.7[/COLOR][/B]</title>
<link>movie=22470.mp4</link>
<info>Duração do filme: 1h, 26min</info>
<genre>Sci-Fi, Terror, Suspense</genre>
<date>2013</date>
</item>
<item>
<title>[B][COLOR white]UMA NOITE DE LOUCURAS[/COLOR] - [COLOR gold]5.2[/COLOR][/B]</title>
<link>movie=16055.mp4</link>
<info>Duração do filme: 1h, 21min</info>
<genre>Comédia</genre>
<date>2017</date>
</item>
<item>
<title>[B][COLOR white]UMA NOITE DE NATAL[/COLOR] - [COLOR gold]6.1[/COLOR][/B]</title>
<link>movie=29476.mp4</link>
<info>Duração do filme: 1h, 27min</info>
<genre>Comédia, Drama, Família, tv movie</genre>
<date>2015</date>
</item>
<item>
<title>[B][COLOR white]UMA NOITE E TANTO[/COLOR] - [COLOR gold]5.7[/COLOR][/B]</title>
<link>movie=22731.mp4</link>
<info>Duração do filme: 1h, 26min</info>
<genre>Comédia</genre>
<date>2017</date>
</item>
<item>
<title>[B][COLOR white]UMA NOITE EM BANGKOK[/COLOR] - [COLOR gold]4.6[/COLOR][/B]</title>
<link>movie=27316.mp4</link>
<info>Duração do filme: 1h, 45min</info>
<genre>Ação, Suspense</genre>
<date>2020</date>
</item>
<item>
<title>[B][COLOR white]UMA NOITE EM MIAMI...[/COLOR] - [COLOR gold]7.2[/COLOR][/B]</title>
<link>movie=27799.mp4</link>
<info>Duração do filme: 1h, 54min</info>
<genre>Drama</genre>
<date>2020</date>
</item>
<item>
<title>[B][COLOR white]UMA NOITE FORA DE SÉRIE[/COLOR] - [COLOR gold]6.3[/COLOR][/B]</title>
<link>movie=15268.mp4</link>
<info>Duração do filme: 1h, 37min</info>
<genre>Comédia</genre>
<date>2010</date>
</item>
<item>
<title>[B][COLOR white]UMA NOITE INFERNAL[/COLOR] - [COLOR gold]5.7[/COLOR][/B]</title>
<link>movie=17473.mp4</link>
<info>Duração do filme: 1h, 29min</info>
<genre>Suspense</genre>
<date>2019</date>
</item>
<item>
<title>[B][COLOR white]UMA NOITE MAIS QUE LOUCA[/COLOR] - [COLOR gold]6.3[/COLOR][/B]</title>
<link>movie=23618.mp4</link>
<info>Duração do filme: 1h, 37min</info>
<genre>Comédia, Drama, Romance</genre>
<date>2011</date>
</item>
<item>
<title>[B][COLOR white]UMA NOITE MALDITA[/COLOR] - [COLOR gold]5.3[/COLOR][/B]</title>
<link>movie=26483.mp4</link>
<info>Duração do filme: 1h, 31min</info>
<genre>Terror</genre>
<date>2013</date>
</item>
<item>
<title>[B][COLOR white]UMA NOITE MUITO LOUCA[/COLOR][/B]</title>
<link>movie=28791.mp4</link>
<info>Duração do filme: 1h, 25min</info>
<genre>Comédia</genre>
<date>1988</date>
</item>
<item>
<title>[B][COLOR white]UMA NOITE NO MUSEU 2[/COLOR] - [COLOR gold]6.0[/COLOR][/B]</title>
<link>movie=22385.mp4</link>
<info>Duração do filme: 1h, 45min</info>
<genre>Aventura, Fantasia, Ação, Comédia, Família</genre>
<date>2009</date>
</item>
<item>
<title>[B][COLOR white]UMA NOITE NO MUSEU 3: O SEGREDO DA TUMBA[/COLOR] - [COLOR gold]6.2[/COLOR][/B]</title>
<link>movie=13209.mp4</link>
<info>Duração do filme: 1h, 37min</info>
<genre>Aventura, Comédia, Fantasia, Família</genre>
<date>2014</date>
</item>
<item>
<title>[B][COLOR white]UMA NOITE NO MUSEU[/COLOR] - [COLOR gold]6.4[/COLOR][/B]</title>
<link>movie=20455.mp4</link>
<info>Duração do filme: 1h, 48min</info>
<genre>Ação, Aventura, Comédia, Família, Fantasia</genre>
<date>2006</date>
</item>
<item>
<title>[B][COLOR white]UMA NOITE PARA ESQUECER[/COLOR] - [COLOR gold]5.4[/COLOR][/B]</title>
<link>movie=26612.mp4</link>
<info>Duração do filme: 1h, 25min</info>
<genre>Suspense</genre>
<date>2013</date>
</item>
<item>
<title>[B][COLOR white]UMA NOITE SOBRE A TERRA[/COLOR] - [COLOR gold]7.8[/COLOR][/B]</title>
<link>movie=14789.mp4</link>
<info>Duração do filme: 2h, 9min</info>
<genre>Comédia, Drama</genre>
<date>1991</date>
</item>
<item>
<title>[B][COLOR white]UMA NOIVA EM APUROS[/COLOR] - [COLOR gold]5.0[/COLOR][/B]</title>
<link>movie=27020.mp4</link>
<info>Duração do filme: 1h, 50min</info>
<genre>Romance, Comédia</genre>
<date>2018</date>
</item>
<item>
<title>[B][COLOR white]UMA NOTÍCIA INESPERADA[/COLOR] - [COLOR gold]6.8[/COLOR][/B]</title>
<link>movie=13825.mp4</link>
<info>Duração do filme: 1h, 23min</info>
<genre>Comédia, Romance</genre>
<date>2014</date>
</item>
<item>
<title>[B][COLOR white]UMA NOVA CHANCE PARA AMAR[/COLOR] - [COLOR gold]6.2[/COLOR][/B]</title>
<link>movie=27369.mp4</link>
<info>Duração do filme: 1h, 32min</info>
<genre>Drama, Romance</genre>
<date>2013</date>
</item>
<item>
<title>[B][COLOR white]UMA NOVA CHANCE[/COLOR] - [COLOR gold]5.8[/COLOR][/B]</title>
<link>movie=18490.mp4</link>
<info>Duração do filme: 1h, 43min</info>
<genre>Romance, Comédia</genre>
<date>2018</date>
</item>
<item>
<title>[B][COLOR white]UMA PATRICINHA DE OUTRO MUNDO[/COLOR] - [COLOR gold]5.5[/COLOR][/B]</title>
<link>movie=14137.mp4</link>
<info>Duração do filme: 1h, 21min</info>
<genre>Drama, Fantasia, Comédia</genre>
<date>2011</date>
</item>
<item>
<title>[B][COLOR white]UMA PAUSA PARA O AMOR[/COLOR] - [COLOR gold]5.5[/COLOR][/B]</title>
<link>movie=14271.mp4</link>
<info>Duração do filme: 1h, 28min</info>
<genre>Drama</genre>
<date>2017</date>
</item>
<item>
<title>[B][COLOR white]UMA PEQUENA AJUDA[/COLOR] - [COLOR gold]5.6[/COLOR][/B]</title>
<link>movie=21505.mp4</link>
<info>Duração do filme: 1h, 49min</info>
<genre>Comédia, Drama, Romance</genre>
<date>2010</date>
</item>
<item>
<title>[B][COLOR white]UMA PESSOA COMUM[/COLOR] - [COLOR gold]5.8[/COLOR][/B]</title>
<link>movie=23775.mp4</link>
<info>Duração do filme: 2h, 1min</info>
<genre>Crime, Ação, Drama</genre>
<date>2017</date>
</item>
<item>
<title>[B][COLOR white]UMA PILHA DE PROBLEMAS: UM MISTÉRIO DE AURORA TEAGARDEN[/COLOR] - [COLOR gold]6.8[/COLOR][/B]</title>
<link>movie=17176.mp4</link>
<info>Duração do filme: 1h, 25min</info>
<genre>Drama, tv movie, Mistério, Crime</genre>
<date>2017</date>
</item>
<item>
<title>[B][COLOR white]UMA PISTOLA PARA DJECA[/COLOR] - [COLOR gold]7.6[/COLOR][/B]</title>
<link>movie=29678.mp4</link>
<info>Duração do filme: 1h, 30min</info>
<genre>Comédia, Faroeste</genre>
<date>1969</date>
</item>
<item>
<title>[B][COLOR white]UMA PISTOLA PARA RINGO[/COLOR] - [COLOR gold]6.5[/COLOR][/B]</title>
<link>movie=28590.mp4</link>
<info>Duração do filme: 1h, 38min</info>
<genre>Faroeste</genre>
<date>1965</date>
</item>
<item>
<title>[B][COLOR white]UMA PONTE LONGE DEMAIS[/COLOR] - [COLOR gold]7.4[/COLOR][/B]</title>
<link>movie=25383.mp4</link>
<info>Duração do filme: 2h, 55min</info>
<genre>Drama, História, Guerra</genre>
<date>1977</date>
</item>
<item>
<title>[B][COLOR white]UMA PRECE ANTES DO AMANHECER[/COLOR][/B]</title>
<link>movie=29475.mp4</link>
<info>Duração do filme: 1h, 56min</info>
<genre>Drama, Ação, Crime</genre>
<date>2018</date>
</item>
<item>
<title>[B][COLOR white]UMA PROMESSA[/COLOR] - [COLOR gold]5.7[/COLOR][/B]</title>
<link>movie=23585.mp4</link>
<info>Duração do filme: 1h, 34min</info>
<genre>Drama, Romance</genre>
<date>2013</date>
</item>
<item>
<title>[B][COLOR white]UMA PROVA DE AMOR[/COLOR] - [COLOR gold]7.4[/COLOR][/B]</title>
<link>movie=18331.mp4</link>
<info>Duração do filme: 1h, 49min</info>
<genre>Drama</genre>
<date>2009</date>
</item>
<item>
<title>[B][COLOR white]UMA PROVA DE FÉ 2: VOLTANDO PARA CASA[/COLOR][/B]</title>
<link>movie=29103.mp4</link>
<info>Duração do filme: 1h, 34min</info>
<genre>Drama, Família</genre>
<date>2019</date>
</item>
<item>
<title>[B][COLOR white]UMA PROVA DE FÉ[/COLOR] - [COLOR gold]4.9[/COLOR][/B]</title>
<link>movie=29104.mp4</link>
<info>Duração do filme: 1h, 28min</info>
<genre>Drama, Família</genre>
<date>2015</date>
</item>
<item>
<title>[B][COLOR white]UMA QUASE DUPLA[/COLOR] - [COLOR gold]5.2[/COLOR][/B]</title>
<link>movie=20794.mp4</link>
<info>Duração do filme: 1h, 35min</info>
<genre>Comédia</genre>
<date>2018</date>
</item>
<item>
<title>[B][COLOR white]UMA QUESTÃO DE ESCOLHA[/COLOR] - [COLOR gold]5.4[/COLOR][/B]</title>
<link>movie=28346.mp4</link>
<info>Duração do filme: 1h, 18min</info>
<genre>Comédia, Romance</genre>
<date>1988</date>
</item>
<item>
<title>[B][COLOR white]UMA QUESTÃO DE FÉ[/COLOR] - [COLOR gold]5.9[/COLOR][/B]</title>
<link>movie=29474.mp4</link>
<info>Duração do filme: 1h, 44min</info>
<genre>Drama</genre>
<date>2017</date>
</item>
<item>
<title>[B][COLOR white]UMA RAZÃO PARA RECOMEÇAR[/COLOR] - [COLOR gold]5.9[/COLOR][/B]</title>
<link>movie=22781.mp4</link>
<info>Duração do filme: 1h, 30min</info>
<genre>Drama, Romance</genre>
<date>2016</date>
</item>
<item>
<title>[B][COLOR white]UMA RAZÃO PARA VENCER[/COLOR] - [COLOR gold]6.5[/COLOR][/B]</title>
<link>movie=25616.mp4</link>
<info>Duração do filme: 1h, 40min</info>
<genre>Drama</genre>
<date>2018</date>
</item>
<item>
<title>[B][COLOR white]UMA RAZÃO PARA VIVER[/COLOR] - [COLOR gold]7.1[/COLOR][/B]</title>
<link>movie=25291.mp4</link>
<info>Duração do filme: 1h, 58min</info>
<genre>Drama, Romance</genre>
<date>2017</date>
</item>
<item>
<title>[B][COLOR white]UMA REPÓRTER EM APUROS[/COLOR] - [COLOR gold]6.6[/COLOR][/B]</title>
<link>movie=24057.mp4</link>
<info>Duração do filme: 1h, 52min</info>
<genre>Guerra, Comédia</genre>
<date>2016</date>
</item>
<item>
<title>[B][COLOR white]UMA RESSACA DE 9 MESES[/COLOR] - [COLOR gold]6.6[/COLOR][/B]</title>
<link>movie=26581.mp4</link>
<info>Duração do filme: 1h, 53min</info>
<genre>Comédia, Romance</genre>
<date>2016</date>
</item>
<item>
<title>[B][COLOR white]UMA SAÍDA DE MESTRE[/COLOR] - [COLOR gold]7.0[/COLOR][/B]</title>
<link>movie=13803.mp4</link>
<info>Duração do filme: 1h, 50min</info>
<genre>Ação, Crime</genre>
<date>2003</date>
</item>
<item>
<title>[B][COLOR white]UMA SECRETÁRIA DE FUTURO[/COLOR] - [COLOR gold]6.8[/COLOR][/B]</title>
<link>movie=25407.mp4</link>
<info>Duração do filme: 1h, 54min</info>
<genre>Comédia, Romance</genre>
<date>1988</date>
</item>
<item>
<title>[B][COLOR white]UMA SECRETÁRIA DE MORTE[/COLOR] - [COLOR gold]5.5[/COLOR][/B]</title>
<link>movie=28185.mp4</link>
<info>Duração do filme: 1h, 30min</info>
<genre>Crime, Comédia</genre>
<date>2010</date>
</item>
<item>
<title>[B][COLOR white]UMA SEGUNDA CHANCE PARA AMAR[/COLOR] - [COLOR gold]6.5[/COLOR][/B]</title>
<link>movie=25758.mp4</link>
<info>Duração do filme: 1h, 42min</info>
<genre>Comédia, Romance, Drama</genre>
<date>2019</date>
</item>
<item>
<title>[B][COLOR white]UMA SEGUNDA CHANCE: RIVAIS![/COLOR] - [COLOR gold]5.5[/COLOR][/B]</title>
<link>movie=29473.mp4</link>
<info>Duração do filme: 1h, 29min</info>
<genre>Drama, Família</genre>
<date>2019</date>
</item>
<item>
<title>[B][COLOR white]UMA SEGUNDA CHANCE[/COLOR] - [COLOR gold]6.7[/COLOR][/B]</title>
<link>movie=28447.mp4</link>
<info>Duração do filme: 1h, 48min</info>
<genre>Romance, Drama</genre>
<date>1991</date>
</item>
<item>
<title>[B][COLOR white]UMA SEGUNDA CHANCE[/COLOR][/B]</title>
<link>movie=29042.mp4</link>
<info>Duração do filme: 1h, 30min</info>
<genre>Família, tv movie</genre>
<date>2014</date>
</item>
<item>
<title>[B][COLOR white]UMA SEMANA A TRÊS[/COLOR] - [COLOR gold]5.4[/COLOR][/B]</title>
<link>movie=20191.mp4</link>
<info>Duração do filme: 1h, 26min</info>
<genre>Comédia, Drama</genre>
<date>2014</date>
</item>
<item>
<title>[B][COLOR white]UMA SEREIA EM PARIS[/COLOR] - [COLOR gold]5.5[/COLOR][/B]</title>
<link>movie=27629.mp4</link>
<info>Duração do filme: 1h, 42min</info>
<genre>Romance, Fantasia, Drama</genre>
<date>2020</date>
</item>
<item>
<title>[B][COLOR white]UMA SKATISTA RADICAL[/COLOR] - [COLOR gold]6.9[/COLOR][/B]</title>
<link>movie=29758.mp4</link>
<info>Duração do filme: 1h, 47min</info>
<genre>Drama</genre>
<date>2021</date>
</item>
<item>
<title>[B][COLOR white]UMA TURMA DO BARULHO[/COLOR] - [COLOR gold]6.3[/COLOR][/B]</title>
<link>movie=13740.mp4</link>
<info>Duração do filme: 1h, 42min</info>
<genre>Comédia, Drama</genre>
<date>2002</date>
</item>
<item>
<title>[B][COLOR white]UMA ÚLTIMA VEZ[/COLOR] - [COLOR gold]5.5[/COLOR][/B]</title>
<link>movie=27009.mp4</link>
<info>Duração do filme: 1h, 35min</info>
<genre>Drama</genre>
<date>2018</date>
</item>
<item>
<title>[B][COLOR white]UMA ÚLTIMA VEZ[/COLOR][/B]</title>
<link>movie=28197.mp4</link>
<info>Duração do filme: 1h, 31min</info>
<genre>Drama</genre>
<date>2018</date>
</item>
<item>
<title>[B][COLOR white]UMA VERDADE INCONVENIENTE[/COLOR] - [COLOR gold]7.4[/COLOR][/B]</title>
<link>movie=16374.mp4</link>
<info>Duração do filme: 1h, 40min</info>
<genre>Documentário</genre>
<date>2006</date>
</item>
<item>
<title>[B][COLOR white]UMA VERDADE MAIS INCONVENIENTE[/COLOR] - [COLOR gold]6.4[/COLOR][/B]</title>
<link>movie=21760.mp4</link>
<info>Duração do filme: 1h, 38min</info>
<genre>Documentário</genre>
<date>2017</date>
</item>
<item>
<title>[B][COLOR white]UMA VERDADE MAIS INCONVENIENTE[/COLOR] - [COLOR gold]7.9[/COLOR][/B]</title>
<link>movie=21838.mp4</link>
<info>Duração do filme: 1h, 14min</info>
<genre>Documentário</genre>
<date>2008</date>
</item>
<item>
<title>[B][COLOR white]UMA VIAGEM AO MUNDO DAS FÁBULAS[/COLOR] - [COLOR gold]7.6[/COLOR][/B]</title>
<link>movie=21132.mp4</link>
<info>Duração do filme: 1h, 15min</info>
<genre>Animação, Família, Fantasia</genre>
<date>2009</date>
</item>
<item>
<title>[B][COLOR white]UMA VIAGEM EXTRAORDINÁRIA[/COLOR] - [COLOR gold]7.1[/COLOR][/B]</title>
<link>movie=23454.mp4</link>
<info>Duração do filme: 1h, 45min</info>
<genre>Aventura, Drama, Família</genre>
<date>2013</date>
</item>
<item>
<title>[B][COLOR white]UMA VIAGEM INFERNAL[/COLOR] - [COLOR gold]4.8[/COLOR][/B]</title>
<link>movie=17331.mp4</link>
<info>Duração do filme: 1h, 32min</info>
<genre>Suspense</genre>
<date>2013</date>
</item>
<item>
<title>[B][COLOR white]UMA VIAGEM PARA ESPANHA[/COLOR] - [COLOR gold]6.6[/COLOR][/B]</title>
<link>movie=13058.mp4</link>
<info>Duração do filme: 1h, 55min</info>
<genre>Comédia, Drama</genre>
<date>2017</date>
</item>
<item>
<title>[B][COLOR white]UMA VIAGEM PARA ITÁLIA[/COLOR] - [COLOR gold]6.6[/COLOR][/B]</title>
<link>movie=13359.mp4</link>
<info>Duração do filme: 1h, 48min</info>
<genre>Comédia, Drama</genre>
<date>2014</date>
</item>
<item>
<title>[B][COLOR white]UMA VIDA COM PROPÓSITO[/COLOR] - [COLOR gold]5.9[/COLOR][/B]</title>
<link>movie=16881.mp4</link>
<info>Duração do filme: 1h, 52min</info>
<genre>Drama</genre>
<date>2016</date>
</item>
<item>
<title>[B][COLOR white]UMA VIDA ILUMINADA[/COLOR] - [COLOR gold]7.4[/COLOR][/B]</title>
<link>movie=17257.mp4</link>
<info>Duração do filme: 1h, 46min</info>
<genre>Comédia, Drama</genre>
<date>2005</date>
</item>
<item>
<title>[B][COLOR white]UMA VIDA MELHOR[/COLOR] - [COLOR gold]7.2[/COLOR][/B]</title>
<link>movie=19978.mp4</link>
<info>Duração do filme: 1h, 38min</info>
<genre>Drama</genre>
<date>2011</date>
</item>
<item>
<title>[B][COLOR white]UMA VIDA OCULTA[/COLOR] - [COLOR gold]7.4[/COLOR][/B]</title>
<link>movie=26723.mp4</link>
<info>Duração do filme: 2h, 54min</info>
<genre>Drama, Guerra, História</genre>
<date>2019</date>
</item>
<item>
<title>[B][COLOR white]UMA VIDA[/COLOR] - [COLOR gold]7.9[/COLOR][/B]</title>
<link>movie=23891.mp4</link>
<info>Duração do filme: 1h, 24min</info>
<genre>Família, Documentário</genre>
<date>2011</date>
</item>
<item>
<title>[B][COLOR white]UN BACIO[/COLOR] - [COLOR gold]6.7[/COLOR][/B]</title>
<link>movie=15541.mp4</link>
<info>Duração do filme: 1h, 41min</info>
<genre>Romance, Comédia, Lgbt</genre>
<date>2016</date>
</item>
<item>
<title>[B][COLOR white]UN FRÈRE[/COLOR] - [COLOR gold]7.1[/COLOR][/B]</title>
<link>movie=24247.mp4</link>
<info>Duração do filme: 1h, 22min</info>
<genre>Drama, Romance</genre>
<date>2018</date>
</item>
<item>
<title>[B][COLOR white]UN HOMME IDÉAL[/COLOR] - [COLOR gold]6.7[/COLOR][/B]</title>
<link>movie=20327.mp4</link>
<info>Duração do filme: 1h, 43min</info>
<genre>Drama, Suspense</genre>
<date>2015</date>
</item>
<item>
<title>[B][COLOR white]UNA FAMIGLIA[/COLOR] - [COLOR gold]5.4[/COLOR][/B]</title>
<link>movie=16508.mp4</link>
<info>Duração do filme: 1h, 37min</info>
<genre>Drama</genre>
<date>2017</date>
</item>
<item>
<title>[B][COLOR white]UNA RAGIONE PER VIVERE E UNA PER MORIRE[/COLOR] - [COLOR gold]6.2[/COLOR][/B]</title>
<link>movie=22004.mp4</link>
<info>Duração do filme: 1h, 19min</info>
<genre>Faroeste</genre>
<date>1972</date>
</item>
<item>
<title>[B][COLOR white]UNA[/COLOR] - [COLOR gold]6.2[/COLOR][/B]</title>
<link>movie=25236.mp4</link>
<info>Duração do filme: 1h, 34min</info>
<genre>Drama, Suspense</genre>
<date>2017</date>
</item>
<item>
<title>[B][COLOR white]UNBOUND[/COLOR][/B]</title>
<link>movie=28986.mp4</link>
<info>Duração do filme: 1h, 37min</info>
<genre>Ação, Crime, Drama, Suspense</genre>
<date>2018</date>
</item>
<item>
<title>[B][COLOR white]UNCAGED[/COLOR] - [COLOR gold]4.0[/COLOR][/B]</title>
<link>movie=17186.mp4</link>
<info>Duração do filme: 1h, 35min</info>
<genre>Terror, Comédia, Suspense</genre>
<date>2016</date>
</item>
<item>
<title>[B][COLOR white]UNCHARTED: LIVE ACTION FAN FILM[/COLOR] - [COLOR gold]8.5[/COLOR][/B]</title>
<link>movie=27102.mp4</link>
<info>Duração do filme: h, 14min</info>
<genre>Ação, Aventura</genre>
<date>2018</date>
</item>
<item>
<title>[B][COLOR white]UNCHARTED[/COLOR][/B]</title>
<link>movie=27822.mp4</link>
<info>Duração do filme: 1h, 20min</info>
<genre>Aventura, Ação</genre>
<date>2022</date>
</item>
<item>
<title>[B][COLOR white]UNCLE JOHN[/COLOR] - [COLOR gold]6.2[/COLOR][/B]</title>
<link>movie=25283.mp4</link>
<info>Duração do filme: 1h, 54min</info>
<genre>Mistério, Drama, Crime, Suspense</genre>
<date>2015</date>
</item>
<item>
<title>[B][COLOR white]UNCLE PECKERHEAD[/COLOR] - [COLOR gold]5.9[/COLOR][/B]</title>
<link>movie=29027.mp4</link>
<info>Duração do filme: 1h, 37min</info>
<genre>Comédia, Terror, Músical</genre>
<date>2020</date>
</item>
<item>
<title>[B][COLOR white]UNDER THE SILVER LAKE[/COLOR] - [COLOR gold]6.5[/COLOR][/B]</title>
<link>movie=19566.mp4</link>
<info>Duração do filme: 2h, 19min</info>
<genre>Drama, Mistério</genre>
<date>2018</date>
</item>
<item>
<title>[B][COLOR white]UNE NOUVELLE AMIE[/COLOR] - [COLOR gold]6.6[/COLOR][/B]</title>
<link>movie=21404.mp4</link>
<info>Duração do filme: 1h, 45min</info>
<genre>Drama</genre>
<date>2014</date>
</item>
<item>
<title>[B][COLOR white]UNEXPECTED[/COLOR] - [COLOR gold]5.7[/COLOR][/B]</title>
<link>movie=18231.mp4</link>
<info>Duração do filme: 1h, 30min</info>
<genre>Comédia, Drama</genre>
<date>2015</date>
</item>
<item>
<title>[B][COLOR white]UNGA ASTRID[/COLOR] - [COLOR gold]7.1[/COLOR][/B]</title>
<link>movie=24755.mp4</link>
<info>Duração do filme: 2h, 3min</info>
<genre>Drama, História</genre>
<date>2018</date>
</item>
<item>
<title>[B][COLOR white]UNICÓRNIO[/COLOR] - [COLOR gold]6.0[/COLOR][/B]</title>
<link>movie=15220.mp4</link>
<info>Duração do filme: 2h, 2min</info>
<genre>Drama</genre>
<date>2017</date>
</item>
<item>
<title>[B][COLOR white]UNIDAS PELA VIDA[/COLOR] - [COLOR gold]6.2[/COLOR][/B]</title>
<link>movie=23423.mp4</link>
<info>Duração do filme: 1h, 31min</info>
<genre>Drama</genre>
<date>2014</date>
</item>
<item>
<title>[B][COLOR white]UNIDOS PELO DESTINO[/COLOR] - [COLOR gold]6.2[/COLOR][/B]</title>
<link>movie=25978.mp4</link>
<info>Duração do filme: 1h, 31min</info>
<genre>Drama, Família</genre>
<date>2016</date>
</item>
<item>
<title>[B][COLOR white]UNION BRIDGE[/COLOR] - [COLOR gold]4.2[/COLOR][/B]</title>
<link>movie=29307.mp4</link>
<info>Duração do filme: 1h, 31min</info>
<genre>Suspense</genre>
<date>2019</date>
</item>
<item>
<title>[B][COLOR white]UNITED[/COLOR] - [COLOR gold]7.4[/COLOR][/B]</title>
<link>movie=15671.mp4</link>
<info>Duração do filme: 1h, 30min</info>
<genre>Drama, História</genre>
<date>2011</date>
</item>
<item>
<title>[B][COLOR white]UNIVERSIDADE MONSTROS[/COLOR] - [COLOR gold]7.3[/COLOR][/B]</title>
<link>movie=24734.mp4</link>
<info>Duração do filme: 1h, 44min</info>
<genre>Animação, Família</genre>
<date>2013</date>
</item>
<item>
<title>[B][COLOR white]UNLEASHED[/COLOR] - [COLOR gold]6.4[/COLOR][/B]</title>
<link>movie=18521.mp4</link>
<info>Duração do filme: 1h, 36min</info>
<genre>Romance, Comédia, Sci-Fi</genre>
<date>2017</date>
</item>
<item>
<title>[B][COLOR white]UNO SCERIFFO EXTRATERRESTRE - POCO EXTRA E MOLTO TERRESTRE[/COLOR] - [COLOR gold]6.2[/COLOR][/B]</title>
<link>movie=17691.mp4</link>
<info>Duração do filme: 1h, 28min</info>
<genre>Comédia, Sci-Fi</genre>
<date>1979</date>
</item>
<item>
<title>[B][COLOR white]UNS BRAÇOS[/COLOR][/B]</title>
<link>movie=27947.mp4</link>
<info>Duração do filme: h, 45min</info>
<genre>Drama</genre>
<date>2009</date>
</item>
<item>
<title>[B][COLOR white]UNSPEAKABLE[/COLOR] - [COLOR gold]5.5[/COLOR][/B]</title>
<link>movie=18341.mp4</link>
<info>Duração do filme: h, 47min</info>
<genre>tv movie, Drama</genre>
<date>2017</date>
</item>
<item>
<title>[B][COLOR white]UNTOLD: BRIGA NA NBA[/COLOR] - [COLOR gold]7.1[/COLOR][/B]</title>
<link>movie=29924.mp4</link>
<info>Duração do filme: 1h, 9min</info>
<genre>Documentário</genre>
<date>2021</date>
</item>
<item>
<title>[B][COLOR white]UNTOLD: CAITLYN JENNER[/COLOR] - [COLOR gold]6.2[/COLOR][/B]</title>
<link>movie=29992.mp4</link>
<info>Duração do filme: 1h, 9min</info>
<genre>Documentário</genre>
<date>2021</date>
</item>
<item>
<title>[B][COLOR white]UNTOLD: FEDERER X FISH[/COLOR] - [COLOR gold]7.4[/COLOR][/B]</title>
<link>movie=30009.mp4</link>
<info>Duração do filme: 1h, 19min</info>
<genre></genre>
<date>2021</date>
</item>
<item>
<title>[B][COLOR white]UNTOLD: PACTO COM O DIABO[/COLOR] - [COLOR gold]7.4[/COLOR][/B]</title>
<link>movie=29949.mp4</link>
<info>Duração do filme: 1h, 17min</info>
<genre>Documentário</genre>
<date>2021</date>
</item>
<item>
<title>[B][COLOR white]UNWRITTEN[/COLOR] - [COLOR gold]3.0[/COLOR][/B]</title>
<link>movie=16120.mp4</link>
<info>Duração do filme: 1h, 24min</info>
<genre>Suspense</genre>
<date>2018</date>
</item>
<item>
<title>[B][COLOR white]UP: ALTAS AVENTURAS[/COLOR] - [COLOR gold]8.2[/COLOR][/B]</title>
<link>movie=24668.mp4</link>
<info>Duração do filme: 1h, 36min</info>
<genre>Animação, Comédia, Família, Aventura</genre>
<date>2009</date>
</item>
<item>
<title>[B][COLOR white]UPA – MEU MONSTRO FAVORITO[/COLOR] - [COLOR gold]6.1[/COLOR][/B]</title>
<link>movie=26582.mp4</link>
<info>Duração do filme: 1h, 51min</info>
<genre>Comédia, Fantasia</genre>
<date>2015</date>
</item>
<item>
<title>[B][COLOR white]UPGRADE: ATUALIZAÇÃO[/COLOR] - [COLOR gold]7.5[/COLOR][/B]</title>
<link>movie=18083.mp4</link>
<info>Duração do filme: 1h, 40min</info>
<genre>Ação, Suspense, Sci-Fi, Terror</genre>
<date>2018</date>
</item>
<item>
<title>[B][COLOR white]UPSIDE-DOWN MAGIC[/COLOR] - [COLOR gold]4.5[/COLOR][/B]</title>
<link>movie=27275.mp4</link>
<info>Duração do filme: 1h, 36min</info>
<genre>Família, Fantasia, tv movie</genre>
<date>2020</date>
</item>
<item>
<title>[B][COLOR white]UPSTARTS[/COLOR] - [COLOR gold]6.7[/COLOR][/B]</title>
<link>movie=29472.mp4</link>
<info>Duração do filme: 1h, 52min</info>
<genre>Comédia, Drama</genre>
<date>2019</date>
</item>
<item>
<title>[B][COLOR white]URI: THE SURGICAL STRIKE[/COLOR] - [COLOR gold]8.2[/COLOR][/B]</title>
<link>movie=29951.mp4</link>
<info>Duração do filme: 2h, 18min</info>
<genre>Ação, Drama, Guerra</genre>
<date>2019</date>
</item>
<item>
<title>[B][COLOR white]USTED NO SABE QUIEN SOY YO?[/COLOR] - [COLOR gold]5.1[/COLOR][/B]</title>
<link>movie=16645.mp4</link>
<info>Duração do filme: 1h, 35min</info>
<genre>Comédia</genre>
<date>2016</date>
</item>
<item>
<title>[B][COLOR white]UTØYA - 22 DE JULHO[/COLOR][/B]</title>
<link>movie=29254.mp4</link>
<info>Duração do filme: 1h, 32min</info>
<genre>História, Drama</genre>
<date>2018</date>
</item>
<item>
<title>[B][COLOR white]V DE VINGANÇA[/COLOR] - [COLOR gold]8.2[/COLOR][/B]</title>
<link>movie=17707.mp4</link>
<info>Duração do filme: 2h, 10min</info>
<genre>Ação, Suspense, Fantasia</genre>
<date>2006</date>
</item>
<item>
<title>[B][COLOR white]V/H/S/2[/COLOR] - [COLOR gold]6.0[/COLOR][/B]</title>
<link>movie=13451.mp4</link>
<info>Duração do filme: 1h, 35min</info>
<genre>Terror, Suspense</genre>
<date>2013</date>
</item>
<item>
<title>[B][COLOR white]V/H/S/94[/COLOR] - [COLOR gold]5.6[/COLOR][/B]</title>
<link>movie=30123.mp4</link>
<info>Duração do filme: 1h, 41min</info>
<genre>Terror, Suspense</genre>
<date>2021</date>
</item>
<item>
<title>[B][COLOR white]V/H/S: VIRAL[/COLOR] - [COLOR gold]4.2[/COLOR][/B]</title>
<link>movie=14579.mp4</link>
<info>Duração do filme: 1h, 21min</info>
<genre>Terror, Suspense</genre>
<date>2014</date>
</item>
<item>
<title>[B][COLOR white]V/H/S[/COLOR] - [COLOR gold]5.8[/COLOR][/B]</title>
<link>movie=15219.mp4</link>
<info>Duração do filme: 1h, 56min</info>
<genre>Suspense, Terror</genre>
<date>2012</date>
</item>
<item>
<title>[B][COLOR white]VÁ E VEJA[/COLOR] - [COLOR gold]8.3[/COLOR][/B]</title>
<link>movie=22848.mp4</link>
<info>Duração do filme: 2h, 22min</info>
<genre>Drama, História, Guerra</genre>
<date>1985</date>
</item>
<item>
<title>[B][COLOR white]VAGINA DENTADA[/COLOR] - [COLOR gold]5.4[/COLOR][/B]</title>
<link>movie=22386.mp4</link>
<info>Duração do filme: 1h, 34min</info>
<genre>Comédia, Terror</genre>
<date>2008</date>
</item>
<item>
<title>[B][COLOR white]VAI QUE COLA - O FILME[/COLOR] - [COLOR gold]5.1[/COLOR][/B]</title>
<link>movie=16096.mp4</link>
<info>Duração do filme: 1h, 33min</info>
<genre>Comédia</genre>
<date>2015</date>
</item>
<item>
<title>[B][COLOR white]VAI QUE COLA 2: O COMEÇO[/COLOR] - [COLOR gold]5.0[/COLOR][/B]</title>
<link>movie=25817.mp4</link>
<info>Duração do filme: 1h, 27min</info>
<genre>Comédia</genre>
<date>2019</date>
</item>
<item>
<title>[B][COLOR white]VAI QUE DÁ CERTO 2[/COLOR][/B]</title>
<link>movie=28684.mp4</link>
<info>Duração do filme: 1h, 39min</info>
<genre>Comédia</genre>
<date>2016</date>
</item>
<item>
<title>[B][COLOR white]VAI QUE DÁ CERTO[/COLOR] - [COLOR gold]5.8[/COLOR][/B]</title>
<link>movie=23817.mp4</link>
<info>Duração do filme: 1h, 27min</info>
<genre>Comédia</genre>
<date>2013</date>
</item>
<item>
<title>[B][COLOR white]VALE DA LUTA[/COLOR] - [COLOR gold]2.6[/COLOR][/B]</title>
<link>movie=25491.mp4</link>
<info>Duração do filme: 1h, 30min</info>
<genre>Ação, Drama</genre>
<date>2016</date>
</item>
<item>
<title>[B][COLOR white]VALE DO PECADO[/COLOR] - [COLOR gold]3.8[/COLOR][/B]</title>
<link>movie=23860.mp4</link>
<info>Duração do filme: 1h, 39min</info>
<genre>Suspense, Drama</genre>
<date>2013</date>
</item>
<item>
<title>[B][COLOR white]VALE TUDO[/COLOR] - [COLOR gold]7.3[/COLOR][/B]</title>
<link>movie=21299.mp4</link>
<info>Duração do filme: 2h, 3min</info>
<genre>Drama, Comédia</genre>
<date>1977</date>
</item>
<item>
<title>[B][COLOR white]VALENTE[/COLOR] - [COLOR gold]6.7[/COLOR][/B]</title>
<link>movie=16099.mp4</link>
<info>Duração do filme: 2h, 2min</info>
<genre>Crime, Drama, Suspense</genre>
<date>2007</date>
</item>
<item>
<title>[B][COLOR white]VALENTE[/COLOR] - [COLOR gold]7.1[/COLOR][/B]</title>
<link>movie=26934.mp4</link>
<info>Duração do filme: 1h, 33min</info>
<genre>Animação, Aventura, Comédia, Família, Ação, Fantasia</genre>
<date>2012</date>
</item>
<item>
<title>[B][COLOR white]VALENTINE[/COLOR] - [COLOR gold]4.6[/COLOR][/B]</title>
<link>movie=15236.mp4</link>
<info>Duração do filme: 1h, 37min</info>
<genre>Ação, Sci-Fi, Ação, Crime, Suspense</genre>
<date>2017</date>
</item>
<item>
<title>[B][COLOR white]VALERIAN E A CIDADE DOS MIL PLANETAS[/COLOR] - [COLOR gold]6.5[/COLOR][/B]</title>
<link>movie=21701.mp4</link>
<info>Duração do filme: 2h, 16min</info>
<genre>Aventura, Sci-Fi, Ação</genre>
<date>2017</date>
</item>
<item>
<title>[B][COLOR white]VALETE DE COPAS[/COLOR] - [COLOR gold]7.2[/COLOR][/B]</title>
<link>movie=15460.mp4</link>
<info>Duração do filme: 1h, 42min</info>
<genre>Drama, Família</genre>
<date>2016</date>
</item>
<item>
<title>[B][COLOR white]VALHALLA: A LENDA DE THOR[/COLOR] - [COLOR gold]5.3[/COLOR][/B]</title>
<link>movie=29170.mp4</link>
<info>Duração do filme: 1h, 45min</info>
<genre>Aventura, Fantasia</genre>
<date>2019</date>
</item>
<item>
<title>[B][COLOR white]VALIANT - UM HERÓI QUE VALE A PENA[/COLOR] - [COLOR gold]5.5[/COLOR][/B]</title>
<link>movie=15256.mp4</link>
<info>Duração do filme: 1h, 16min</info>
<genre>Animação, Família, Aventura, Comédia, Guerra</genre>
<date>2005</date>
</item>
<item>
<title>[B][COLOR white]VALLEY GIRL[/COLOR] - [COLOR gold]6.4[/COLOR][/B]</title>
<link>movie=12898.mp4</link>
<info>Duração do filme: 1h, 39min</info>
<genre>Comédia, Romance</genre>
<date>1983</date>
</item>
<item>
<title>[B][COLOR white]VALLEY OF BONES[/COLOR] - [COLOR gold]4.2[/COLOR][/B]</title>
<link>movie=15665.mp4</link>
<info>Duração do filme: 1h, 30min</info>
<genre>Faroeste, Crime, Suspense</genre>
<date>2017</date>
</item>
<item>
<title>[B][COLOR white]VALLEY OF DITCHES[/COLOR] - [COLOR gold]3.9[/COLOR][/B]</title>
<link>movie=17301.mp4</link>
<info>Duração do filme: 1h, 17min</info>
<genre>Suspense, Crime, Drama, Terror, Mistério</genre>
<date>2017</date>
</item>
<item>
<title>[B][COLOR white]VALLEY UPRISING[/COLOR] - [COLOR gold]8.1[/COLOR][/B]</title>
<link>movie=29875.mp4</link>
<info>Duração do filme: 1h, 39min</info>
<genre>Aventura, Documentário</genre>
<date>2014</date>
</item>
<item>
<title>[B][COLOR white]VAMP - A NOITE DOS VAMPIROS[/COLOR][/B]</title>
<link>movie=28703.mp4</link>
<info>Duração do filme: 1h, 33min</info>
<genre>Comédia, Terror</genre>
<date>1986</date>
</item>
<item>
<title>[B][COLOR white]VAMP U[/COLOR] - [COLOR gold]3.9[/COLOR][/B]</title>
<link>movie=17920.mp4</link>
<info>Duração do filme: 1h, 40min</info>
<genre>Ação, Comédia, Terror</genre>
<date>2013</date>
</item>
<item>
<title>[B][COLOR white]VAMPIRAS[/COLOR] - [COLOR gold]5.2[/COLOR][/B]</title>
<link>movie=22598.mp4</link>
<info>Duração do filme: 1h, 33min</info>
<genre>Comédia, Romance, Terror</genre>
<date>2012</date>
</item>
<item>
<title>[B][COLOR white]VAMPIRE'S KISS[/COLOR] - [COLOR gold]6.0[/COLOR][/B]</title>
<link>movie=20063.mp4</link>
<info>Duração do filme: 1h, 43min</info>
<genre>Comédia, Terror</genre>
<date>1988</date>
</item>
<item>
<title>[B][COLOR white]VAMPIRE BATS[/COLOR] - [COLOR gold]4.2[/COLOR][/B]</title>
<link>movie=26122.mp4</link>
<info>Duração do filme: 2h, 0min</info>
<genre>Terror, Sci-Fi, Suspense, tv movie, Drama</genre>
<date>2005</date>
</item>
<item>
<title>[B][COLOR white]VAMPIRE HUNTER D: BLOODLUST[/COLOR] - [COLOR gold]7.7[/COLOR][/B]</title>
<link>movie=25517.mp4</link>
<info>Duração do filme: 1h, 43min</info>
<genre>Ação, Aventura, Animação, Fantasia, Terror, Mistério, Sci-Fi</genre>
<date>2000</date>
</item>
<item>
<title>[B][COLOR white]VAMPIRE HUNTER D[/COLOR] - [COLOR gold]7.2[/COLOR][/B]</title>
<link>movie=17998.mp4</link>
<info>Duração do filme: 1h, 20min</info>
<genre>Animação, Fantasia, Terror</genre>
<date>1985</date>
</item>
<item>
<title>[B][COLOR white]VAMPIRO EM VEGAS[/COLOR][/B]</title>
<link>movie=29049.mp4</link>
<info>Duração do filme: 1h, 22min</info>
<genre>Terror</genre>
<date>2009</date>
</item>
<item>
<title>[B][COLOR white]VAMPIROS DE ALMAS[/COLOR] - [COLOR gold]7.7[/COLOR][/B]</title>
<link>movie=20877.mp4</link>
<info>Duração do filme: 1h, 20min</info>
<genre>Terror, Sci-Fi</genre>
<date>1956</date>
</item>
<item>
<title>[B][COLOR white]VAMPIROS DE JOHN CARPENTER[/COLOR] - [COLOR gold]6.2[/COLOR][/B]</title>
<link>movie=19692.mp4</link>
<info>Duração do filme: 1h, 48min</info>
<genre>Ação, Drama, Fantasia, Terror, Suspense, Faroeste</genre>
<date>1998</date>
</item>
<item>
<title>[B][COLOR white]VAMPIROS X THE BRONX[/COLOR] - [COLOR gold]4.7[/COLOR][/B]</title>
<link>movie=27402.mp4</link>
<info>Duração do filme: 1h, 26min</info>
<genre>Comédia, Terror</genre>
<date>2020</date>
</item>
<item>
<title>[B][COLOR white]VAMPS - A MORTE NÃO EXISTE PARA O AMOR[/COLOR] - [COLOR gold]4.2[/COLOR][/B]</title>
<link>movie=25381.mp4</link>
<info>Duração do filme: 1h, 30min</info>
<genre>Terror, Ação, Fantasia, Suspense</genre>
<date>2017</date>
</item>
<item>
<title>[B][COLOR white]VAN HELSING: O CAÇADOR DE MONSTROS[/COLOR] - [COLOR gold]6.1[/COLOR][/B]</title>
<link>movie=14463.mp4</link>
<info>Duração do filme: 2h, 12min</info>
<genre>Terror, Aventura, Ação</genre>
<date>2004</date>
</item>
<item>
<title>[B][COLOR white]VANGUARDA[/COLOR] - [COLOR gold]3.2[/COLOR][/B]</title>
<link>movie=28340.mp4</link>
<info>Duração do filme: 1h, 29min</info>
<genre>Ação, Terror, Sci-Fi</genre>
<date>2008</date>
</item>
<item>
<title>[B][COLOR white]VANILLA SKY[/COLOR] - [COLOR gold]6.9[/COLOR][/B]</title>
<link>movie=25243.mp4</link>
<info>Duração do filme: 2h, 16min</info>
<genre>Romance, Sci-Fi, Fantasia, Drama, Suspense</genre>
<date>2001</date>
</item>
<item>
<title>[B][COLOR white]VANISHING TIME: A BOY WHO RETURNED[/COLOR] - [COLOR gold]7.2[/COLOR][/B]</title>
<link>movie=15842.mp4</link>
<info>Duração do filme: 2h, 9min</info>
<genre>Romance, Fantasia, Drama</genre>
<date>2016</date>
</item>
<item>
<title>[B][COLOR white]VANQUISH[/COLOR] - [COLOR gold]2.7[/COLOR][/B]</title>
<link>movie=28042.mp4</link>
<info>Duração do filme: 1h, 36min</info>
<genre>Ação, Crime, Suspense</genre>
<date>2021</date>
</item>
<item>
<title>[B][COLOR white]VARJOJA PARATIISISSA[/COLOR] - [COLOR gold]7.5[/COLOR][/B]</title>
<link>movie=15648.mp4</link>
<info>Duração do filme: 1h, 12min</info>
<genre>Drama, Comédia</genre>
<date>1986</date>
</item>
<item>
<title>[B][COLOR white]VAULT[/COLOR] - [COLOR gold]5.4[/COLOR][/B]</title>
<link>movie=19836.mp4</link>
<info>Duração do filme: 1h, 39min</info>
<genre>Crime, Drama</genre>
<date>2019</date>
</item>
<item>
<title>[B][COLOR white]VAXXED: DO ENCOBRIMENTO À CATÁSTROFE[/COLOR] - [COLOR gold]5.1[/COLOR][/B]</title>
<link>movie=20688.mp4</link>
<info>Duração do filme: 1h, 31min</info>
<genre>Documentário, Fantasia</genre>
<date>2016</date>
</item>
<item>
<title>[B][COLOR white]VAZANTE[/COLOR] - [COLOR gold]6.2[/COLOR][/B]</title>
<link>movie=15857.mp4</link>
<info>Duração do filme: 1h, 40min</info>
<genre>Drama</genre>
<date>2017</date>
</item>
<item>
<title>[B][COLOR white]VEIA DE LUTADOR[/COLOR] - [COLOR gold]5.6[/COLOR][/B]</title>
<link>movie=20014.mp4</link>
<info>Duração do filme: 1h, 45min</info>
<genre>Ação, Aventura, Crime, Drama, Suspense</genre>
<date>2009</date>
</item>
<item>
<title>[B][COLOR white]VEÍCULO 19[/COLOR] - [COLOR gold]4.9[/COLOR][/B]</title>
<link>movie=18976.mp4</link>
<info>Duração do filme: 1h, 25min</info>
<genre>Suspense</genre>
<date>2013</date>
</item>
<item>
<title>[B][COLOR white]VELHOS TEMPOS[/COLOR] - [COLOR gold]4.0[/COLOR][/B]</title>
<link>movie=21196.mp4</link>
<info>Duração do filme: 2h, 1min</info>
<genre>Drama</genre>
<date>2016</date>
</item>
<item>
<title>[B][COLOR white]VELOCIDADE MÁXIMA 2[/COLOR] - [COLOR gold]3.9[/COLOR][/B]</title>
<link>movie=19914.mp4</link>
<info>Duração do filme: 2h, 1min</info>
<genre>Ação, Aventura, Suspense</genre>
<date>1997</date>
</item>
<item>
<title>[B][COLOR white]VELOCIDADE MÁXIMA[/COLOR] - [COLOR gold]7.2[/COLOR][/B]</title>
<link>movie=23625.mp4</link>
<info>Duração do filme: 1h, 56min</info>
<genre>Ação, Aventura, Crime</genre>
<date>1994</date>
</item>
<item>
<title>[B][COLOR white]VELOCIDADE MORTAL[/COLOR] - [COLOR gold]4.1[/COLOR][/B]</title>
<link>movie=21918.mp4</link>
<info>Duração do filme: 1h, 42min</info>
<genre>Crime, Drama, Suspense</genre>
<date>2018</date>
</item>
<item>
<title>[B][COLOR white]VELOCIDADE SEM LIMITES[/COLOR] - [COLOR gold]4.0[/COLOR][/B]</title>
<link>movie=28115.mp4</link>
<info>Duração do filme: 1h, 35min</info>
<genre>Ação, Drama, Suspense</genre>
<date>2007</date>
</item>
<item>
<title>[B][COLOR white]VELOCITY TRAP[/COLOR] - [COLOR gold]4.6[/COLOR][/B]</title>
<link>movie=14140.mp4</link>
<info>Duração do filme: 1h, 26min</info>
<genre>Sci-Fi</genre>
<date>1999</date>
</item>
<item>
<title>[B][COLOR white]VELOZ COMO O VENTO[/COLOR] - [COLOR gold]7.3[/COLOR][/B]</title>
<link>movie=25846.mp4</link>
<info>Duração do filme: 1h, 59min</info>
<genre>Drama</genre>
<date>2016</date>
</item>
<item>
<title>[B][COLOR white]VELOZES & FURIOSOS 7[/COLOR] - [COLOR gold]7.2[/COLOR][/B]</title>
<link>movie=16131.mp4</link>
<info>Duração do filme: 2h, 17min</info>
<genre>Ação, Crime, Suspense</genre>
<date>2015</date>
</item>
<item>
<title>[B][COLOR white]VELOZES & FURIOSOS 9[/COLOR] - [COLOR gold]5.4[/COLOR][/B]</title>
<link>movie=25724.mp4</link>
<info>Duração do filme: 2h, 25min</info>
<genre>Ação, Suspense</genre>
<date>2021</date>
</item>
<item>
<title>[B][COLOR white]VELOZES E FURIOSOS 4[/COLOR] - [COLOR gold]6.6[/COLOR][/B]</title>
<link>movie=15685.mp4</link>
<info>Duração do filme: 1h, 47min</info>
<genre>Ação, Crime, Drama, Suspense</genre>
<date>2009</date>
</item>
<item>
<title>[B][COLOR white]VELOZES E FURIOSOS 5 - OPERAÇÃO RIO[/COLOR] - [COLOR gold]7.3[/COLOR][/B]</title>
<link>movie=19188.mp4</link>
<info>Duração do filme: 2h, 10min</info>
<genre>Ação, Suspense, Crime</genre>
<date>2011</date>
</item>
<item>
<title>[B][COLOR white]VELOZES E FURIOSOS 6[/COLOR] - [COLOR gold]7.1[/COLOR][/B]</title>
<link>movie=13861.mp4</link>
<info>Duração do filme: 2h, 11min</info>
<genre>Ação, Suspense, Crime</genre>
<date>2013</date>
</item>
<item>
<title>[B][COLOR white]VELOZES E FURIOSOS 8[/COLOR] - [COLOR gold]6.7[/COLOR][/B]</title>
<link>movie=24834.mp4</link>
<info>Duração do filme: 2h, 16min</info>
<genre>Ação, Crime, Suspense</genre>
<date>2017</date>
</item>
<item>
<title>[B][COLOR white]VELOZES E FURIOSOS: DESAFIO EM TÓQUIO[/COLOR] - [COLOR gold]6.0[/COLOR][/B]</title>
<link>movie=23403.mp4</link>
<info>Duração do filme: 1h, 44min</info>
<genre>Ação, Crime, Drama, Suspense</genre>
<date>2006</date>
</item>
<item>
<title>[B][COLOR white]VELOZES E FURIOSOS: HOBBS & SHAW[/COLOR] - [COLOR gold]6.5[/COLOR][/B]</title>
<link>movie=15820.mp4</link>
<info>Duração do filme: 2h, 17min</info>
<genre>Ação, Aventura, Comédia</genre>
<date>2019</date>
</item>
<item>
<title>[B][COLOR white]VELOZES E FURIOSOS: TURBO-CHARGED PRELUDE[/COLOR] - [COLOR gold]6.2[/COLOR][/B]</title>
<link>movie=27313.mp4</link>
<info>Duração do filme: h, 6min</info>
<genre>Ação</genre>
<date>2003</date>
</item>
<item>
<title>[B][COLOR white]VELOZES E FURIOSOS[/COLOR] - [COLOR gold]6.8[/COLOR][/B]</title>
<link>movie=19605.mp4</link>
<info>Duração do filme: 1h, 46min</info>
<genre>Ação, Crime, Suspense</genre>
<date>2001</date>
</item>
<item>
<title>[B][COLOR white]VELOZES E MORTAIS[/COLOR] - [COLOR gold]5.7[/COLOR][/B]</title>
<link>movie=17479.mp4</link>
<info>Duração do filme: 1h, 20min</info>
<genre>Ação, Crime, Suspense</genre>
<date>2004</date>
</item>
<item>
<title>[B][COLOR white]VELUDO AZUL[/COLOR] - [COLOR gold]7.8[/COLOR][/B]</title>
<link>movie=16203.mp4</link>
<info>Duração do filme: 2h, 0min</info>
<genre>Crime, Mistério, Suspense</genre>
<date>1986</date>
</item>
<item>
<title>[B][COLOR white]VELVET GOLDMINE[/COLOR] - [COLOR gold]7.0[/COLOR][/B]</title>
<link>movie=23255.mp4</link>
<info>Duração do filme: 2h, 4min</info>
<genre>Drama, Músical</genre>
<date>1998</date>
</item>
<item>
<title>[B][COLOR white]VEM DANÇAR COMIGO[/COLOR] - [COLOR gold]7.2[/COLOR][/B]</title>
<link>movie=25410.mp4</link>
<info>Duração do filme: 1h, 34min</info>
<genre>Comédia, Drama, Romance</genre>
<date>1992</date>
</item>
<item>
<title>[B][COLOR white]VEM DANÇAR[/COLOR] - [COLOR gold]6.6[/COLOR][/B]</title>
<link>movie=27378.mp4</link>
<info>Duração do filme: 1h, 58min</info>
<genre>Comédia, Músical, Drama</genre>
<date>2006</date>
</item>
<item>
<title>[B][COLOR white]VEM MORDER COMIGO[/COLOR] - [COLOR gold]5.9[/COLOR][/B]</title>
<link>movie=26390.mp4</link>
<info>Duração do filme: 1h, 30min</info>
<genre>Terror, Comédia</genre>
<date>1995</date>
</item>
<item>
<title>[B][COLOR white]VENCER OU MORRER[/COLOR] - [COLOR gold]5.7[/COLOR][/B]</title>
<link>movie=18329.mp4</link>
<info>Duração do filme: 1h, 34min</info>
<genre>Ação</genre>
<date>1993</date>
</item>
<item>
<title>[B][COLOR white]VENDE-SE ESTA CASA[/COLOR] - [COLOR gold]3.2[/COLOR][/B]</title>
<link>movie=18921.mp4</link>
<info>Duração do filme: 1h, 34min</info>
<genre>Suspense, Terror</genre>
<date>2018</date>
</item>
<item>
<title>[B][COLOR white]VENDE-SE IMÓVEL[/COLOR] - [COLOR gold]3.6[/COLOR][/B]</title>
<link>movie=16735.mp4</link>
<info>Duração do filme: 1h, 12min</info>
<genre>Terror</genre>
<date>2019</date>
</item>
<item>
<title>[B][COLOR white]VENDETTA[/COLOR] - [COLOR gold]5.8[/COLOR][/B]</title>
<link>movie=17717.mp4</link>
<info>Duração do filme: 1h, 42min</info>
<genre>Ação, Suspense</genre>
<date>2013</date>
</item>
<item>
<title>[B][COLOR white]VENDIDA[/COLOR] - [COLOR gold]6.8[/COLOR][/B]</title>
<link>movie=18218.mp4</link>
<info>Duração do filme: 1h, 37min</info>
<genre>Drama</genre>
<date>2016</date>
</item>
<item>
<title>[B][COLOR white]VENDO OU ALUGO[/COLOR] - [COLOR gold]5.2[/COLOR][/B]</title>
<link>movie=15691.mp4</link>
<info>Duração do filme: 1h, 28min</info>
<genre>Comédia</genre>
<date>2013</date>
</item>
<item>
<title>[B][COLOR white]VENEZA[/COLOR] - [COLOR gold]7.5[/COLOR][/B]</title>
<link>movie=30140.mp4</link>
<info>Duração do filme: 1h, 31min</info>
<genre>Drama, Comédia, Romance</genre>
<date>2021</date>
</item>
<item>
<title>[B][COLOR white]VENGEANCE[/COLOR] - [COLOR gold]4.3[/COLOR][/B]</title>
<link>movie=18346.mp4</link>
<info>Duração do filme: 1h, 35min</info>
<genre>Ação</genre>
<date>2018</date>
</item>
<item>
<title>[B][COLOR white]VENOM: TEMPO DE CARNIFICINA[/COLOR] - [COLOR gold]6.2[/COLOR][/B]</title>
<link>movie=27817.mp4</link>
<info>Duração do filme: 1h, 37min</info>
<genre>Ação, Sci-Fi</genre>
<date>2021</date>
</item>
<item>
<title>[B][COLOR white]VENOM[/COLOR] - [COLOR gold]4.6[/COLOR][/B]</title>
<link>movie=26568.mp4</link>
<info>Duração do filme: 1h, 25min</info>
<genre>Terror, Suspense</genre>
<date>2005</date>
</item>
<item>
<title>[B][COLOR white]VENOM[/COLOR] - [COLOR gold]6.7[/COLOR][/B]</title>
<link>movie=25659.mp4</link>
<info>Duração do filme: 1h, 52min</info>
<genre>Sci-Fi, Ação</genre>
<date>2018</date>
</item>
<item>
<title>[B][COLOR white]VENTOS DA LIBERDADE[/COLOR] - [COLOR gold]7.5[/COLOR][/B]</title>
<link>movie=21601.mp4</link>
<info>Duração do filme: 2h, 7min</info>
<genre>Drama, Guerra</genre>
<date>2006</date>
</item>
<item>
<title>[B][COLOR white]VENTOS DA LIBERDADE[/COLOR] - [COLOR gold]7.5[/COLOR][/B]</title>
<link>movie=25284.mp4</link>
<info>Duração do filme: 2h, 6min</info>
<genre>Suspense, História, Drama</genre>
<date>2018</date>
</item>
<item>
<title>[B][COLOR white]VENTOS DE AGOSTO[/COLOR] - [COLOR gold]6.2[/COLOR][/B]</title>
<link>movie=18137.mp4</link>
<info>Duração do filme: 1h, 17min</info>
<genre>Documentário, Mistério</genre>
<date>2014</date>
</item>
<item>
<title>[B][COLOR white]VENUS IN FURS[/COLOR] - [COLOR gold]4.7[/COLOR][/B]</title>
<link>movie=13936.mp4</link>
<info>Duração do filme: 1h, 5min</info>
<genre>Drama</genre>
<date>1967</date>
</item>
<item>
<title>[B][COLOR white]VENUS WARS[/COLOR] - [COLOR gold]6.7[/COLOR][/B]</title>
<link>movie=15233.mp4</link>
<info>Duração do filme: 1h, 42min</info>
<genre>Ação, Animação, Sci-Fi</genre>
<date>1989</date>
</item>
<item>
<title>[B][COLOR white]VENUS[/COLOR] - [COLOR gold]7.1[/COLOR][/B]</title>
<link>movie=14414.mp4</link>
<info>Duração do filme: 1h, 35min</info>
<genre>Comédia, Drama, Romance</genre>
<date>2006</date>
</item>
<item>
<title>[B][COLOR white]VERÃO 2003[/COLOR] - [COLOR gold]5.4[/COLOR][/B]</title>
<link>movie=21361.mp4</link>
<info>Duração do filme: 1h, 35min</info>
<genre>Comédia</genre>
<date>2018</date>
</item>
<item>
<title>[B][COLOR white]VERÃO DE 84[/COLOR] - [COLOR gold]6.7[/COLOR][/B]</title>
<link>movie=23745.mp4</link>
<info>Duração do filme: 1h, 45min</info>
<genre>Suspense, Mistério, Drama, Terror</genre>
<date>2018</date>
</item>
<item>
<title>[B][COLOR white]VERÃO DE 85[/COLOR] - [COLOR gold]6.9[/COLOR][/B]</title>
<link>movie=27522.mp4</link>
<info>Duração do filme: 1h, 40min</info>
<genre>Drama</genre>
<date>2020</date>
</item>
<item>
<title>[B][COLOR white]VERÃO DE 92[/COLOR] - [COLOR gold]6.9[/COLOR][/B]</title>
<link>movie=26502.mp4</link>
<info>Duração do filme: 1h, 50min</info>
<genre>Drama, Comédia</genre>
<date>2015</date>
</item>
<item>
<title>[B][COLOR white]VERÃO DE ILUSÕES[/COLOR] - [COLOR gold]6.6[/COLOR][/B]</title>
<link>movie=28649.mp4</link>
<info>Duração do filme: 1h, 36min</info>
<genre>Comédia, Drama</genre>
<date>1976</date>
</item>
<item>
<title>[B][COLOR white]VERÃO EM STATEN ISLAND[/COLOR] - [COLOR gold]5.6[/COLOR][/B]</title>
<link>movie=13422.mp4</link>
<info>Duração do filme: 1h, 48min</info>
<genre>Comédia</genre>
<date>2015</date>
</item>
<item>
<title>[B][COLOR white]VERÃO OBSCURO[/COLOR] - [COLOR gold]4.2[/COLOR][/B]</title>
<link>movie=13383.mp4</link>
<info>Duração do filme: 1h, 21min</info>
<genre>Suspense, Terror</genre>
<date>2015</date>
</item>
<item>
<title>[B][COLOR white]VERCINGÉTORIX : LA LÉGENDE DU DRUIDE ROI[/COLOR] - [COLOR gold]2.7[/COLOR][/B]</title>
<link>movie=15615.mp4</link>
<info>Duração do filme: 2h, 4min</info>
<genre>Ação</genre>
<date>2001</date>
</item>
<item>
<title>[B][COLOR white]VERDADE E JUSTIÇA[/COLOR] - [COLOR gold]8.6[/COLOR][/B]</title>
<link>movie=27090.mp4</link>
<info>Duração do filme: 2h, 45min</info>
<genre>Drama, História</genre>
<date>2019</date>
</item>
<item>
<title>[B][COLOR white]VERDADE OCULTA[/COLOR] - [COLOR gold]5.0[/COLOR][/B]</title>
<link>movie=26639.mp4</link>
<info>Duração do filme: 1h, 20min</info>
<genre>Suspense, Crime, Drama, Mistério</genre>
<date>2017</date>
</item>
<item>
<title>[B][COLOR white]VERDADE OU DESAFIO[/COLOR] - [COLOR gold]5.2[/COLOR][/B]</title>
<link>movie=22824.mp4</link>
<info>Duração do filme: 1h, 40min</info>
<genre>Suspense, Terror</genre>
<date>2018</date>
</item>
<item>
<title>[B][COLOR white]VERDADES E MENTIRAS[/COLOR] - [COLOR gold]7.8[/COLOR][/B]</title>
<link>movie=22280.mp4</link>
<info>Duração do filme: 1h, 29min</info>
<genre>Documentário</genre>
<date>1975</date>
</item>